{"surah":24,"ayahs":[{"ayah":1,"words":[{"word":"سُورَةٌ","ref":"24:1:1","start":8.518,"end":10.366},{"word":"أَنزَلْنَٰهَا","ref":"24:1:2","start":10.366,"end":13.6},{"word":"وَفَرَضْنَٰهَا","ref":"24:1:3","start":13.6,"end":16.834},{"word":"وَأَنزَلْنَا","ref":"24:1:4","start":16.834,"end":20.068},{"word":"فِيهَا","ref":"24:1:5","start":20.068,"end":21.916},{"word":"ءَايَٰتِۢ","ref":"24:1:6","start":21.916,"end":23.764},{"word":"بَيِّنَٰتٖ","ref":"24:1:7","start":23.764,"end":25.612},{"word":"لَّعَلَّكُمْ","ref":"24:1:8","start":25.612,"end":27.922},{"word":"تَذَّكَّرُونَۖ","ref":"24:1:9","start":28.124,"end":29.554}]},{"ayah":2,"words":[{"word":"اَ۬لزَّانِيَةُ","ref":"24:2:1","start":33.5,"end":36.146},{"word":"وَالزَّانِے","ref":"24:2:2","start":36.252,"end":38.02},{"word":"فَاجْلِدُواْ","ref":"24:2:3","start":38.02,"end":40.083},{"word":"كُلَّ","ref":"24:2:4","start":40.083,"end":40.672},{"word":"وَٰحِدٖ","ref":"24:2:5","start":40.672,"end":41.556},{"word":"مِّنْهُمَا","ref":"24:2:6","start":41.556,"end":43.03},{"word":"مِاْئَةَ","ref":"24:2:7","start":43.03,"end":44.503},{"word":"جَلْدَةٖۖ","ref":"24:2:8","start":44.503,"end":45.682},{"word":"وَلَا","ref":"24:2:9","start":48.27,"end":49.512},{"word":"تَأْخُذْكُم","ref":"24:2:10","start":49.512,"end":51.995},{"word":"بِهِمَا","ref":"24:2:11","start":51.995,"end":53.65},{"word":"رَأْفَةٞ","ref":"24:2:12","start":53.83,"end":55.236},{"word":"فِے","ref":"24:2:13","start":55.236,"end":55.587},{"word":"دِينِ","ref":"24:2:14","start":55.587,"end":56.642},{"word":"اِ۬للَّهِ","ref":"24:2:15","start":56.642,"end":58.048},{"word":"إِن","ref":"24:2:16","start":58.048,"end":58.751},{"word":"كُنتُمْ","ref":"24:2:17","start":58.751,"end":60.157},{"word":"تُؤْمِنُونَ","ref":"24:2:18","start":60.157,"end":61.914},{"word":"بِاللَّهِ","ref":"24:2:19","start":61.914,"end":63.672},{"word":"وَالْيَوْمِ","ref":"24:2:20","start":63.672,"end":65.781},{"word":"اِ۬لْأٓخِرِۖ","ref":"24:2:21","start":65.781,"end":67.89},{"word":"وَلْيَشْهَدْ","ref":"24:2:22","start":70.588,"end":72.975},{"word":"عَذَابَهُمَا","ref":"24:2:23","start":72.975,"end":75.76},{"word":"طَآئِفَةٞ","ref":"24:2:24","start":75.76,"end":77.749},{"word":"مِّنَ","ref":"24:2:25","start":77.749,"end":78.545},{"word":"اَ۬لْمُؤْمِنِينَۖ","ref":"24:2:26","start":78.545,"end":81.33}]},{"ayah":3,"words":[{"word":"اَ۬لزَّانِے","ref":"24:3:1","start":84.604,"end":86.781},{"word":"لَا","ref":"24:3:2","start":86.781,"end":87.651},{"word":"يَنكِحُ","ref":"24:3:3","start":87.651,"end":89.392},{"word":"إِلَّا","ref":"24:3:4","start":89.392,"end":90.698},{"word":"زَانِيَةً","ref":"24:3:5","start":90.698,"end":92.875},{"word":"أَوْ","ref":"24:3:6","start":92.875,"end":93.745},{"word":"مُشْرِكَةٗ","ref":"24:3:7","start":93.745,"end":95.922},{"word":"وَالزَّانِيَةُ","ref":"24:3:8","start":96.06,"end":98.827},{"word":"لَا","ref":"24:3:9","start":98.827,"end":99.519},{"word":"يَنكِحُهَا","ref":"24:3:10","start":99.519,"end":101.595},{"word":"إِلَّا","ref":"24:3:11","start":101.595,"end":102.633},{"word":"زَانٍ","ref":"24:3:12","start":102.633,"end":103.67},{"word":"أَوْ","ref":"24:3:13","start":103.67,"end":104.362},{"word":"مُشْرِكٞۖ","ref":"24:3:14","start":104.362,"end":105.746},{"word":"وَحُرِّمَ","ref":"24:3:15","start":107.942,"end":109.457},{"word":"ذَٰلِكَ","ref":"24:3:16","start":109.457,"end":110.593},{"word":"عَلَى","ref":"24:3:17","start":110.593,"end":111.351},{"word":"اَ۬لْمُؤْمِنِينَۖ","ref":"24:3:18","start":111.351,"end":114.002}]},{"ayah":4,"words":[{"word":"وَالذِينَ","ref":"24:4:1","start":116.892,"end":118.66},{"word":"يَرْمُونَ","ref":"24:4:2","start":118.66,"end":120.134},{"word":"اَ۬لْمُحْصَنَٰتِ","ref":"24:4:3","start":120.134,"end":122.197},{"word":"ثُمَّ","ref":"24:4:4","start":122.197,"end":122.787},{"word":"لَمْ","ref":"24:4:5","start":122.787,"end":123.376},{"word":"يَأْتُواْ","ref":"24:4:6","start":123.376,"end":124.85},{"word":"يَأْتُواْ","ref":"24:4:6","start":124.988,"end":126.688},{"word":"بِأَرْبَعَةِ","ref":"24:4:7","start":126.688,"end":128.728},{"word":"شُهَدَآءَ","ref":"24:4:8","start":128.728,"end":130.767},{"word":"فَاجْلِدُوهُمْ","ref":"24:4:9","start":130.767,"end":133.487},{"word":"ثَمَٰنِينَ","ref":"24:4:10","start":133.487,"end":135.187},{"word":"جَلْدَةٗۖ","ref":"24:4:11","start":135.187,"end":136.547},{"word":"وَلَا","ref":"24:4:12","start":136.547,"end":137.567},{"word":"تَقْبَلُواْ","ref":"24:4:13","start":137.567,"end":139.606},{"word":"لَهُمْ","ref":"24:4:14","start":139.606,"end":140.626},{"word":"شَهَٰدَةً","ref":"24:4:15","start":140.626,"end":141.986},{"word":"أَبَداٗۖ","ref":"24:4:16","start":141.986,"end":143.346},{"word":"وَأُوْلَٰٓئِكَ","ref":"24:4:17","start":146.076,"end":148.747},{"word":"هُمُ","ref":"24:4:18","start":148.747,"end":149.638},{"word":"اُ۬لْفَٰسِقُونَ","ref":"24:4:19","start":149.638,"end":152.754}]},{"ayah":5,"words":[{"word":"إِلَّا","ref":"24:5:1","start":155.278,"end":156.354},{"word":"اَ۬لذِينَ","ref":"24:5:2","start":156.354,"end":158.148},{"word":"تَابُواْ","ref":"24:5:3","start":158.148,"end":159.942},{"word":"مِنۢ","ref":"24:5:4","start":159.942,"end":160.66},{"word":"بَعْدِ","ref":"24:5:5","start":160.66,"end":161.736},{"word":"ذَٰلِكَ","ref":"24:5:6","start":161.736,"end":162.813},{"word":"وَأَصْلَحُواْ","ref":"24:5:7","start":162.813,"end":165.324},{"word":"فَإِنَّ","ref":"24:5:8","start":165.324,"end":166.401},{"word":"اَ۬للَّهَ","ref":"24:5:9","start":166.401,"end":167.836},{"word":"غَفُورٞ","ref":"24:5:10","start":167.836,"end":169.271},{"word":"رَّحِيمٞۖ","ref":"24:5:11","start":169.271,"end":170.706}]},{"ayah":6,"words":[{"word":"وَالذِينَ","ref":"24:6:1","start":173.34,"end":175.53},{"word":"يَرْمُونَ","ref":"24:6:2","start":175.53,"end":177.355},{"word":"أَزْوَٰجَهُمْ","ref":"24:6:3","start":177.355,"end":179.545},{"word":"وَلَمْ","ref":"24:6:4","start":179.545,"end":180.64},{"word":"يَكُن","ref":"24:6:5","start":180.64,"end":181.735},{"word":"لَّهُمْ","ref":"24:6:6","start":181.735,"end":182.83},{"word":"شُهَدَآءُ","ref":"24:6:7","start":182.83,"end":185.02},{"word":"اِ۪لَّا","ref":"24:6:8","start":185.02,"end":186.115},{"word":"أَنفُسُهُمْ","ref":"24:6:9","start":186.115,"end":188.305},{"word":"فَشَهَٰدَةُ","ref":"24:6:10","start":188.305,"end":190.13},{"word":"أَحَدِهِمْ","ref":"24:6:11","start":190.13,"end":191.955},{"word":"أَرْبَعَ","ref":"24:6:12","start":191.955,"end":193.415},{"word":"شَهَٰدَٰتِۢ","ref":"24:6:13","start":193.415,"end":194.875},{"word":"بِاللَّهِ","ref":"24:6:14","start":194.875,"end":196.7},{"word":"إِنَّهُۥ","ref":"24:6:15","start":196.7,"end":198.16},{"word":"لَمِنَ","ref":"24:6:16","start":198.16,"end":199.255},{"word":"اَ۬لصَّٰدِقِينَ","ref":"24:6:17","start":199.255,"end":201.81}]},{"ayah":7,"words":[{"word":"وَالْخَٰمِسَةُ","ref":"24:7:1","start":204.316,"end":206.752},{"word":"أَن","ref":"24:7:2","start":206.752,"end":207.449},{"word":"لَّعْنَتُ","ref":"24:7:3","start":207.449,"end":208.841},{"word":"اُ۬للَّهِ","ref":"24:7:4","start":208.841,"end":210.233},{"word":"عَلَيْهِ","ref":"24:7:5","start":210.233,"end":211.625},{"word":"إِن","ref":"24:7:6","start":211.625,"end":212.321},{"word":"كَانَ","ref":"24:7:7","start":212.321,"end":213.365},{"word":"مِنَ","ref":"24:7:8","start":213.365,"end":214.062},{"word":"اَ۬لْكَٰذِبِينَۖ","ref":"24:7:9","start":214.062,"end":216.498}]},{"ayah":8,"words":[{"word":"وَيَدْرَؤُاْ","ref":"24:8:1","start":219.132,"end":220.944},{"word":"عَنْهَا","ref":"24:8:2","start":220.944,"end":222.394},{"word":"اَ۬لْعَذَابَ","ref":"24:8:3","start":222.394,"end":224.569},{"word":"أَن","ref":"24:8:4","start":224.569,"end":225.294},{"word":"تَشْهَدَ","ref":"24:8:5","start":225.294,"end":226.744},{"word":"أَرْبَعَ","ref":"24:8:6","start":226.744,"end":228.193},{"word":"شَهَٰدَٰتِۢ","ref":"24:8:7","start":228.193,"end":229.643},{"word":"بِاللَّهِ","ref":"24:8:8","start":229.643,"end":231.456},{"word":"إِنَّهُۥ","ref":"24:8:9","start":231.456,"end":232.905},{"word":"لَمِنَ","ref":"24:8:10","start":232.905,"end":233.993},{"word":"اَ۬لْكَٰذِبِينَ","ref":"24:8:11","start":233.993,"end":236.53}]},{"ayah":9,"words":[{"word":"وَالْخَٰمِسَةُ","ref":"24:9:1","start":239.388,"end":241.895},{"word":"أَنْ","ref":"24:9:2","start":241.895,"end":242.611},{"word":"غَضِبَ","ref":"24:9:3","start":242.611,"end":243.685},{"word":"اَ۬للَّهُ","ref":"24:9:4","start":243.685,"end":245.118},{"word":"عَلَيْهَا","ref":"24:9:5","start":245.118,"end":246.908},{"word":"إِن","ref":"24:9:6","start":246.908,"end":247.625},{"word":"كَانَ","ref":"24:9:7","start":247.625,"end":248.699},{"word":"مِنَ","ref":"24:9:8","start":248.699,"end":249.415},{"word":"اَ۬لصَّٰدِقِينَۖ","ref":"24:9:9","start":249.415,"end":251.922}]},{"ayah":10,"words":[{"word":"وَلَوْلَا","ref":"24:10:1","start":254.908,"end":256.802},{"word":"فَضْلُ","ref":"24:10:2","start":256.802,"end":257.939},{"word":"اُ۬للَّهِ","ref":"24:10:3","start":257.939,"end":259.454},{"word":"عَلَيْكُمْ","ref":"24:10:4","start":259.454,"end":261.348},{"word":"وَرَحْمَتُهُۥ","ref":"24:10:5","start":261.348,"end":264},{"word":"وَأَنَّ","ref":"24:10:6","start":264,"end":265.136},{"word":"اَ۬للَّهَ","ref":"24:10:7","start":265.136,"end":266.651},{"word":"تَوَّابٌ","ref":"24:10:8","start":266.651,"end":268.167},{"word":"حَكِيمٌۖ","ref":"24:10:9","start":268.167,"end":269.682}]},{"ayah":11,"words":[{"word":"۞","ref":"24:11:1","start":272.686,"end":272.686},{"word":"إِنَّ","ref":"24:11:2","start":272.686,"end":273.521},{"word":"اَ۬لذِينَ","ref":"24:11:3","start":273.521,"end":275.608},{"word":"جَآءُو","ref":"24:11:4","start":275.608,"end":277.695},{"word":"بِالْإِفْكِ","ref":"24:11:5","start":277.695,"end":280.199},{"word":"عُصْبَةٞ","ref":"24:11:6","start":280.199,"end":281.868},{"word":"مِّنكُمْ","ref":"24:11:7","start":281.868,"end":283.538},{"word":"لَا","ref":"24:11:8","start":285.422,"end":286.168},{"word":"تَحْسِبُوهُ","ref":"24:11:9","start":286.168,"end":288.405},{"word":"شَرّاٗ","ref":"24:11:10","start":288.405,"end":289.523},{"word":"لَّكُمۖ","ref":"24:11:11","start":289.523,"end":290.642},{"word":"بَلْ","ref":"24:11:12","start":292.27,"end":293.026},{"word":"هُوَ","ref":"24:11:13","start":293.026,"end":293.782},{"word":"خَيْرٞ","ref":"24:11:14","start":293.782,"end":294.916},{"word":"لَّكُمْۖ","ref":"24:11:15","start":294.916,"end":296.05},{"word":"لِكُلِّ","ref":"24:11:16","start":298.894,"end":300.213},{"word":"اِ۪مْرِےٕٖ","ref":"24:11:17","start":300.213,"end":301.971},{"word":"مِّنْهُم","ref":"24:11:18","start":301.971,"end":303.73},{"word":"مَّا","ref":"24:11:19","start":303.982,"end":304.376},{"word":"اَ۪كْتَسَبَ","ref":"24:11:20","start":304.376,"end":305.36},{"word":"مِنَ","ref":"24:11:21","start":305.36,"end":305.754},{"word":"اَ۬لْإِثْمِۖ","ref":"24:11:22","start":305.754,"end":306.738},{"word":"وَالذِے","ref":"24:11:23","start":308.87,"end":310.398},{"word":"تَوَلَّىٰ","ref":"24:11:24","start":310.398,"end":311.545},{"word":"كِبْرَهُۥ","ref":"24:11:25","start":311.545,"end":313.455},{"word":"مِنْهُمْ","ref":"24:11:26","start":313.455,"end":314.983},{"word":"لَهُۥ","ref":"24:11:27","start":314.983,"end":316.129},{"word":"عَذَابٌ","ref":"24:11:28","start":316.129,"end":317.658},{"word":"عَظِيمٞۖ","ref":"24:11:29","start":317.658,"end":319.186}]},{"ayah":12,"words":[{"word":"لَّوْلَا","ref":"24:12:1","start":321.894,"end":323.266},{"word":"إِذْ","ref":"24:12:2","start":323.266,"end":323.952},{"word":"سَمِعْتُمُوهُ","ref":"24:12:3","start":323.952,"end":326.353},{"word":"ظَنَّ","ref":"24:12:4","start":326.353,"end":327.039},{"word":"اَ۬لْمُؤْمِنُونَ","ref":"24:12:5","start":327.039,"end":329.44},{"word":"وَالْمُؤْمِنَٰتُ","ref":"24:12:6","start":329.44,"end":331.841},{"word":"بِأَنفُسِهِمْ","ref":"24:12:7","start":331.841,"end":334.242},{"word":"خَيْراٗ","ref":"24:12:8","start":334.242,"end":335.614},{"word":"وَقَالُواْ","ref":"24:12:9","start":335.614,"end":337.672},{"word":"هَٰذَا","ref":"24:12:10","start":337.672,"end":338.701},{"word":"إِفْكٞ","ref":"24:12:11","start":338.701,"end":339.73},{"word":"مُّبِينٞۖ","ref":"24:12:12","start":339.942,"end":342.482}]},{"ayah":13,"words":[{"word":"لَّوْلَا","ref":"24:13:1","start":345.638,"end":347.12},{"word":"جَآءُو","ref":"24:13:2","start":347.12,"end":348.972},{"word":"عَلَيْهِ","ref":"24:13:3","start":348.972,"end":350.453},{"word":"بِأَرْبَعَةِ","ref":"24:13:4","start":350.453,"end":352.676},{"word":"شُهَدَآءَۖ","ref":"24:13:5","start":352.676,"end":354.898},{"word":"فَإِذْ","ref":"24:13:6","start":356.398,"end":356.956},{"word":"لَمْ","ref":"24:13:7","start":356.956,"end":357.328},{"word":"يَأْتُواْ","ref":"24:13:8","start":357.328,"end":358.258},{"word":"يَأْتُواْ","ref":"24:13:8","start":358.396,"end":360.159},{"word":"بِالشُّهَدَآءِ","ref":"24:13:9","start":360.159,"end":363.333},{"word":"فَأُوْلَٰٓئِكَ","ref":"24:13:10","start":363.333,"end":365.448},{"word":"عِندَ","ref":"24:13:11","start":365.448,"end":366.506},{"word":"اَ۬للَّهِ","ref":"24:13:12","start":366.506,"end":367.916},{"word":"هُمُ","ref":"24:13:13","start":367.916,"end":368.622},{"word":"اُ۬لْكَٰذِبُونَۖ","ref":"24:13:14","start":368.622,"end":371.09}]},{"ayah":14,"words":[{"word":"وَلَوْلَا","ref":"24:14:1","start":373.532,"end":375.06},{"word":"فَضْلُ","ref":"24:14:2","start":375.06,"end":375.977},{"word":"اُ۬للَّهِ","ref":"24:14:3","start":375.977,"end":377.2},{"word":"عَلَيْكُمْ","ref":"24:14:4","start":377.2,"end":378.728},{"word":"وَرَحْمَتُهُۥ","ref":"24:14:5","start":378.728,"end":380.868},{"word":"فِے","ref":"24:14:6","start":380.868,"end":381.173},{"word":"اِ۬لدُّنْيَا","ref":"24:14:7","start":381.173,"end":383.007},{"word":"وَالْأٓخِرَةِ","ref":"24:14:8","start":383.007,"end":385.452},{"word":"لَمَسَّكُمْ","ref":"24:14:9","start":385.452,"end":386.981},{"word":"فِے","ref":"24:14:10","start":386.981,"end":387.286},{"word":"مَا","ref":"24:14:11","start":387.286,"end":387.898},{"word":"أَفَضْتُمْ","ref":"24:14:12","start":387.898,"end":389.426},{"word":"أَفَضْتُمْ","ref":"24:14:12","start":389.628,"end":391.145},{"word":"فِيهِ","ref":"24:14:13","start":391.145,"end":392.055},{"word":"عَذَابٌ","ref":"24:14:14","start":392.055,"end":393.269},{"word":"عَظِيمٌ","ref":"24:14:15","start":393.269,"end":394.482}]},{"ayah":15,"words":[{"word":"إِذْ","ref":"24:15:1","start":397.102,"end":397.845},{"word":"تَلَقَّوْنَهُۥ","ref":"24:15:2","start":397.845,"end":400.446},{"word":"بِأَلْسِنَتِكُمْ","ref":"24:15:3","start":400.446,"end":403.419},{"word":"وَتَقُولُونَ","ref":"24:15:4","start":403.419,"end":406.02},{"word":"بِأَفْوَاهِكُم","ref":"24:15:5","start":406.02,"end":408.992},{"word":"مَّا","ref":"24:15:6","start":408.992,"end":409.735},{"word":"لَيْسَ","ref":"24:15:7","start":409.735,"end":410.85},{"word":"لَكُم","ref":"24:15:8","start":410.85,"end":411.965},{"word":"بِهِۦ","ref":"24:15:9","start":411.965,"end":413.079},{"word":"عِلْمٞ","ref":"24:15:10","start":413.079,"end":414.194},{"word":"وَتَحْسِبُونَهُۥ","ref":"24:15:11","start":414.3,"end":417.347},{"word":"هَيِّناٗ","ref":"24:15:12","start":417.347,"end":418.702},{"word":"وَهْوَ","ref":"24:15:13","start":418.702,"end":419.717},{"word":"عِندَ","ref":"24:15:14","start":419.717,"end":420.733},{"word":"اَ۬للَّهِ","ref":"24:15:15","start":420.733,"end":422.088},{"word":"عَظِيمٞۖ","ref":"24:15:16","start":422.088,"end":423.442}]},{"ayah":16,"words":[{"word":"وَلَوْلَا","ref":"24:16:1","start":425.82,"end":427.733},{"word":"إِذْ","ref":"24:16:2","start":427.733,"end":428.498},{"word":"سَمِعْتُمُوهُ","ref":"24:16:3","start":428.498,"end":431.177},{"word":"قُلْتُم","ref":"24:16:4","start":431.177,"end":432.707},{"word":"مَّا","ref":"24:16:5","start":432.707,"end":433.473},{"word":"يَكُونُ","ref":"24:16:6","start":433.473,"end":435.003},{"word":"لَنَا","ref":"24:16:7","start":435.003,"end":436.151},{"word":"أَن","ref":"24:16:8","start":436.151,"end":436.916},{"word":"نَّتَكَلَّمَ","ref":"24:16:9","start":436.916,"end":438.829},{"word":"بِهَٰذَا","ref":"24:16:10","start":438.829,"end":440.36},{"word":"سُبْحَٰنَكَ","ref":"24:16:11","start":440.36,"end":442.273},{"word":"هَٰذَا","ref":"24:16:12","start":442.273,"end":443.421},{"word":"بُهْتَٰنٌ","ref":"24:16:13","start":443.421,"end":444.951},{"word":"عَظِيمٞۖ","ref":"24:16:14","start":444.951,"end":446.482}]},{"ayah":17,"words":[{"word":"يَعِظُكُمُ","ref":"24:17:1","start":449.628,"end":451.496},{"word":"اُ۬للَّهُ","ref":"24:17:2","start":451.496,"end":452.991},{"word":"أَن","ref":"24:17:3","start":452.991,"end":453.738},{"word":"تَعُودُواْ","ref":"24:17:4","start":453.738,"end":455.98},{"word":"لِمِثْلِهِۦ","ref":"24:17:5","start":455.98,"end":458.222},{"word":"أَبَداً","ref":"24:17:6","start":458.222,"end":459.716},{"word":"إِن","ref":"24:17:7","start":459.716,"end":460.463},{"word":"كُنتُم","ref":"24:17:8","start":460.463,"end":461.958},{"word":"مُّؤْمِنِينَۖ","ref":"24:17:9","start":461.958,"end":463.826}]},{"ayah":18,"words":[{"word":"وَيُبَيِّنُ","ref":"24:18:1","start":466.172,"end":467.911},{"word":"اُ۬للَّهُ","ref":"24:18:2","start":467.911,"end":469.303},{"word":"لَكُمُ","ref":"24:18:3","start":469.303,"end":470.347},{"word":"اُ۬لْأٓيَٰتِۖ","ref":"24:18:4","start":470.347,"end":472.434},{"word":"وَاللَّهُ","ref":"24:18:5","start":474.012,"end":475.99},{"word":"عَلِيمٌ","ref":"24:18:6","start":475.99,"end":477.572},{"word":"حَكِيمٌۖ","ref":"24:18:7","start":477.572,"end":479.154}]},{"ayah":19,"words":[{"word":"إِنَّ","ref":"24:19:1","start":482.19,"end":482.777},{"word":"اَ۬لذِينَ","ref":"24:19:2","start":482.777,"end":484.246},{"word":"يُحِبُّونَ","ref":"24:19:3","start":484.246,"end":485.714},{"word":"يُحِبُّونَ","ref":"24:19:3","start":485.852,"end":487.448},{"word":"أَن","ref":"24:19:4","start":487.448,"end":488.087},{"word":"تَشِيعَ","ref":"24:19:5","start":488.087,"end":489.364},{"word":"اَ۬لْفَٰحِشَةُ","ref":"24:19:6","start":489.364,"end":491.279},{"word":"فِے","ref":"24:19:7","start":491.279,"end":491.598},{"word":"اِ۬لذِينَ","ref":"24:19:8","start":491.598,"end":493.194},{"word":"ءَامَنُواْ","ref":"24:19:9","start":493.194,"end":495.11},{"word":"لَهُمْ","ref":"24:19:10","start":495.11,"end":496.068},{"word":"عَذَابٌ","ref":"24:19:11","start":496.068,"end":497.345},{"word":"أَلِيمٞ","ref":"24:19:12","start":497.345,"end":498.621},{"word":"فِے","ref":"24:19:13","start":498.621,"end":498.941},{"word":"اِ۬لدُّنْيَا","ref":"24:19:14","start":498.941,"end":500.856},{"word":"وَالْأٓخِرَةِۖ","ref":"24:19:15","start":500.856,"end":503.41},{"word":"وَاللَّهُ","ref":"24:19:16","start":506.588,"end":508.353},{"word":"يَعْلَمُۖ","ref":"24:19:17","start":508.353,"end":509.765},{"word":"وَأَنتُمْ","ref":"24:19:18","start":509.765,"end":511.53},{"word":"لَا","ref":"24:19:19","start":511.53,"end":512.236},{"word":"تَعْلَمُونَۖ","ref":"24:19:20","start":512.236,"end":514.354}]},{"ayah":20,"words":[{"word":"وَلَوْلَا","ref":"24:20:1","start":516.476,"end":518.272},{"word":"فَضْلُ","ref":"24:20:2","start":518.272,"end":519.349},{"word":"اُ۬للَّهِ","ref":"24:20:3","start":519.349,"end":520.786},{"word":"عَلَيْكُمْ","ref":"24:20:4","start":520.786,"end":522.581},{"word":"وَرَحْمَتُهُۥ","ref":"24:20:5","start":522.581,"end":525.095},{"word":"وَأَنَّ","ref":"24:20:6","start":525.095,"end":526.172},{"word":"اَ۬للَّهَ","ref":"24:20:7","start":526.172,"end":527.609},{"word":"رَءُوفٞ","ref":"24:20:8","start":527.609,"end":529.045},{"word":"رَّحِيمٞۖ","ref":"24:20:9","start":529.045,"end":530.482}]},{"ayah":21,"words":[{"word":"۞","ref":"24:21:1","start":533.262,"end":533.262},{"word":"يَٰأَيُّهَا","ref":"24:21:2","start":533.262,"end":534.523},{"word":"اَ۬لذِينَ","ref":"24:21:3","start":534.523,"end":535.784},{"word":"ءَامَنُواْ","ref":"24:21:4","start":535.784,"end":537.297},{"word":"لَا","ref":"24:21:5","start":537.297,"end":537.801},{"word":"تَتَّبِعُواْ","ref":"24:21:6","start":537.801,"end":539.314},{"word":"تَتَّبِعُواْ","ref":"24:21:6","start":539.484,"end":541.424},{"word":"خُطْوَٰتِ","ref":"24:21:7","start":541.424,"end":542.718},{"word":"اِ۬لشَّيْطَٰنِۖ","ref":"24:21:8","start":542.718,"end":544.658},{"word":"وَمَنْ","ref":"24:21:9","start":546.094,"end":546.823},{"word":"يَّتَّبِعْ","ref":"24:21:10","start":546.823,"end":547.794},{"word":"يَّتَّبِعْ","ref":"24:21:10","start":547.974,"end":549.377},{"word":"خُطْوَٰتِ","ref":"24:21:11","start":549.377,"end":550.779},{"word":"اِ۬لشَّيْطَٰنِ","ref":"24:21:12","start":550.779,"end":552.883},{"word":"فَإِنَّهُۥ","ref":"24:21:13","start":552.883,"end":554.637},{"word":"يَأْمُرُ","ref":"24:21:14","start":554.637,"end":556.039},{"word":"بِالْفَحْشَآءِ","ref":"24:21:15","start":556.039,"end":559.195},{"word":"وَالْمُنكَرِۖ","ref":"24:21:16","start":559.195,"end":561.65},{"word":"وَلَوْلَا","ref":"24:21:17","start":563.42,"end":565.281},{"word":"فَضْلُ","ref":"24:21:18","start":565.281,"end":566.397},{"word":"اُ۬للَّهِ","ref":"24:21:19","start":566.397,"end":567.885},{"word":"عَلَيْكُمْ","ref":"24:21:20","start":567.885,"end":569.746},{"word":"وَرَحْمَتُهُۥ","ref":"24:21:21","start":569.746,"end":572.351},{"word":"مَا","ref":"24:21:22","start":572.351,"end":573.095},{"word":"زَكَىٰ","ref":"24:21:23","start":573.095,"end":573.839},{"word":"مِنكُم","ref":"24:21:24","start":573.839,"end":575.328},{"word":"مِّنْ","ref":"24:21:25","start":575.328,"end":576.072},{"word":"أَحَدٍ","ref":"24:21:26","start":576.072,"end":577.188},{"word":"أَبَداٗۖ","ref":"24:21:27","start":577.188,"end":578.677},{"word":"وَلَٰكِنَّ","ref":"24:21:28","start":578.677,"end":580.165},{"word":"اَ۬للَّهَ","ref":"24:21:29","start":580.165,"end":581.654},{"word":"يُزَكِّے","ref":"24:21:30","start":581.654,"end":582.77},{"word":"مَنْ","ref":"24:21:31","start":589.038,"end":589.528},{"word":"يَّشَآءُۖ","ref":"24:21:32","start":589.528,"end":590.753},{"word":"وَاللَّهُ","ref":"24:21:33","start":590.753,"end":591.978},{"word":"سَمِيعٌ","ref":"24:21:34","start":591.978,"end":592.958},{"word":"عَلِيمٞۖ","ref":"24:21:35","start":592.958,"end":593.938}]},{"ayah":22,"words":[{"word":"وَلَا","ref":"24:22:1","start":597.966,"end":598.724},{"word":"يَأْتَلِ","ref":"24:22:2","start":598.724,"end":599.736},{"word":"أُوْلُواْ","ref":"24:22:3","start":599.736,"end":601},{"word":"اُ۬لْفَضْلِ","ref":"24:22:4","start":601,"end":602.264},{"word":"مِنكُمْ","ref":"24:22:5","start":602.264,"end":603.275},{"word":"وَالسَّعَةِ","ref":"24:22:6","start":603.275,"end":604.792},{"word":"أَنْ","ref":"24:22:7","start":604.792,"end":605.298},{"word":"يُّؤْتُواْ","ref":"24:22:8","start":605.478,"end":606.715},{"word":"أُوْلِے","ref":"24:22:9","start":606.715,"end":607.644},{"word":"اِ۬لْقُرْبَىٰ","ref":"24:22:10","start":607.644,"end":609.19},{"word":"وَالْمَسَٰكِينَ","ref":"24:22:11","start":609.19,"end":611.665},{"word":"وَالْمُهَٰجِرِينَ","ref":"24:22:12","start":611.665,"end":614.449},{"word":"فِے","ref":"24:22:13","start":614.449,"end":614.759},{"word":"سَبِيلِ","ref":"24:22:14","start":614.759,"end":615.996},{"word":"اِ۬للَّهِۖ","ref":"24:22:15","start":615.996,"end":617.234},{"word":"وَلْيَعْفُواْ","ref":"24:22:16","start":617.234,"end":619.399},{"word":"وَلْيَصْفَحُواْۖ","ref":"24:22:17","start":619.399,"end":621.874},{"word":"أَلَا","ref":"24:22:18","start":624.494,"end":625.587},{"word":"تُحِبُّونَ","ref":"24:22:19","start":625.587,"end":627.409},{"word":"أَنْ","ref":"24:22:20","start":627.409,"end":628.138},{"word":"يَّغْفِرَ","ref":"24:22:21","start":628.138,"end":629.595},{"word":"اَ۬للَّهُ","ref":"24:22:22","start":629.595,"end":631.053},{"word":"لَكُمْۖ","ref":"24:22:23","start":631.053,"end":632.146},{"word":"وَاللَّهُ","ref":"24:22:24","start":633.244,"end":635.209},{"word":"غَفُورٞ","ref":"24:22:25","start":635.209,"end":636.782},{"word":"رَّحِيمٌۖ","ref":"24:22:26","start":636.782,"end":638.354}]},{"ayah":23,"words":[{"word":"إِنَّ","ref":"24:23:1","start":640.238,"end":640.896},{"word":"اَ۬لذِينَ","ref":"24:23:2","start":640.896,"end":642.54},{"word":"يَرْمُونَ","ref":"24:23:3","start":642.54,"end":644.184},{"word":"اَ۬لْمُحْصَنَٰتِ","ref":"24:23:4","start":644.184,"end":646.486},{"word":"اِ۬لْغَٰفِلَٰتِ","ref":"24:23:5","start":646.486,"end":648.46},{"word":"اِ۬لْمُؤْمِنَٰتِ","ref":"24:23:6","start":648.46,"end":650.433},{"word":"لُعِنُواْ","ref":"24:23:7","start":650.433,"end":652.077},{"word":"فِے","ref":"24:23:8","start":652.077,"end":652.406},{"word":"اِ۬لدُّنْيَا","ref":"24:23:9","start":652.406,"end":654.379},{"word":"وَالْأٓخِرَةِ","ref":"24:23:10","start":654.379,"end":657.01},{"word":"وَلَهُمْ","ref":"24:23:11","start":659.59,"end":661.066},{"word":"عَذَابٌ","ref":"24:23:12","start":661.066,"end":662.542},{"word":"عَظِيمٞ","ref":"24:23:13","start":662.542,"end":664.018}]},{"ayah":24,"words":[{"word":"يَوْمَ","ref":"24:24:1","start":666.286,"end":667.287},{"word":"تَشْهَدُ","ref":"24:24:2","start":667.287,"end":668.622},{"word":"عَلَيْهِمْ","ref":"24:24:3","start":668.622,"end":670.29},{"word":"أَلْسِنَتُهُمْ","ref":"24:24:4","start":670.29,"end":672.626},{"word":"وَأَيْدِيهِمْ","ref":"24:24:5","start":672.626,"end":674.962},{"word":"وَأَرْجُلُهُم","ref":"24:24:6","start":674.962,"end":677.298},{"word":"بِمَا","ref":"24:24:7","start":677.298,"end":678.299},{"word":"كَانُواْ","ref":"24:24:8","start":678.299,"end":679.968},{"word":"يَعْمَلُونَۖ","ref":"24:24:9","start":679.968,"end":681.97}]},{"ayah":25,"words":[{"word":"يَوْمَئِذٖ","ref":"24:25:1","start":687.814,"end":688.695},{"word":"يُوَفِّيهِمُ","ref":"24:25:2","start":688.695,"end":690.017},{"word":"اُ۬للَّهُ","ref":"24:25:3","start":690.017,"end":690.899},{"word":"دِينَهُمُ","ref":"24:25:4","start":690.899,"end":692.001},{"word":"اُ۬لْحَقَّۖ","ref":"24:25:5","start":692.001,"end":692.882},{"word":"وَيَعْلَمُونَ","ref":"24:25:6","start":693.084,"end":695.627},{"word":"أَنَّ","ref":"24:25:7","start":695.627,"end":696.353},{"word":"اَ۬للَّهَ","ref":"24:25:8","start":696.353,"end":697.806},{"word":"هُوَ","ref":"24:25:9","start":697.806,"end":698.533},{"word":"اَ۬لْحَقُّ","ref":"24:25:10","start":698.533,"end":699.986},{"word":"اُ۬لْمُبِينُۖ","ref":"24:25:11","start":700.124,"end":702.226}]},{"ayah":26,"words":[{"word":"اُ۬لْخَبِيثَٰتُ","ref":"24:26:1","start":705.212,"end":707.753},{"word":"لِلْخَبِيثِينَ","ref":"24:26:2","start":707.753,"end":710.657},{"word":"وَالْخَبِيثُونَ","ref":"24:26:3","start":710.657,"end":713.925},{"word":"لِلْخَبِيثَٰتِۖ","ref":"24:26:4","start":713.925,"end":716.466},{"word":"وَالطَّيِّبَٰتُ","ref":"24:26:5","start":722.3,"end":723.623},{"word":"لِلطَّيِّبِينَ","ref":"24:26:6","start":723.623,"end":724.946},{"word":"وَالطَّيِّبَٰتُ","ref":"24:26:5","start":727.964,"end":730.162},{"word":"لِلطَّيِّبِينَ","ref":"24:26:6","start":731.964,"end":733.454},{"word":"وَالطَّيِّبُونَ","ref":"24:26:7","start":733.454,"end":735.156},{"word":"لِلطَّيِّبَٰتِۖ","ref":"24:26:8","start":735.156,"end":736.433},{"word":"أُوْلَٰٓئِكَ","ref":"24:26:9","start":736.433,"end":737.498},{"word":"مُبَرَّءُونَ","ref":"24:26:10","start":737.498,"end":738.775},{"word":"مِمَّا","ref":"24:26:11","start":738.775,"end":739.413},{"word":"يَقُولُونَۖ","ref":"24:26:12","start":739.413,"end":740.69},{"word":"لَهُم","ref":"24:26:13","start":742.03,"end":743.447},{"word":"مَّغْفِرَةٞ","ref":"24:26:14","start":743.447,"end":745.808},{"word":"وَرِزْقٞ","ref":"24:26:15","start":745.808,"end":747.697},{"word":"كَرِيمٞۖ","ref":"24:26:16","start":747.697,"end":749.586}]},{"ayah":27,"words":[{"word":"يَٰأَيُّهَا","ref":"24:27:1","start":752.508,"end":754.087},{"word":"اَ۬لذِينَ","ref":"24:27:2","start":754.087,"end":755.666},{"word":"ءَامَنُواْ","ref":"24:27:3","start":755.666,"end":757.56},{"word":"لَا","ref":"24:27:4","start":757.56,"end":758.192},{"word":"تَدْخُلُواْ","ref":"24:27:5","start":758.192,"end":760.086},{"word":"بِيُوتاً","ref":"24:27:6","start":760.086,"end":761.665},{"word":"غَيْرَ","ref":"24:27:7","start":761.665,"end":762.612},{"word":"بِيُوتِكُمْ","ref":"24:27:8","start":762.612,"end":764.507},{"word":"حَتَّىٰ","ref":"24:27:9","start":764.507,"end":765.138},{"word":"حَتَّىٰ","ref":"24:27:9","start":765.422,"end":766.113},{"word":"تَسْتَأْنِسُواْ","ref":"24:27:10","start":766.113,"end":768.877},{"word":"وَتُسَلِّمُواْ","ref":"24:27:11","start":768.877,"end":771.296},{"word":"عَلَىٰ","ref":"24:27:12","start":771.296,"end":771.987},{"word":"أَهْلِهَاۖ","ref":"24:27:13","start":771.987,"end":773.714},{"word":"ذَٰلِكُمْ","ref":"24:27:14","start":776.454,"end":778.437},{"word":"خَيْرٞ","ref":"24:27:15","start":778.437,"end":779.924},{"word":"لَّكُمْ","ref":"24:27:16","start":779.924,"end":781.411},{"word":"لَعَلَّكُمْ","ref":"24:27:17","start":781.411,"end":783.89},{"word":"تَذَّكَّرُونَۖ","ref":"24:27:18","start":784.124,"end":785.65}]},{"ayah":28,"words":[{"word":"فَإِن","ref":"24:28:1","start":788.206,"end":789.214},{"word":"لَّمْ","ref":"24:28:2","start":789.214,"end":789.887},{"word":"تَجِدُواْ","ref":"24:28:3","start":789.887,"end":791.567},{"word":"فِيهَا","ref":"24:28:4","start":791.567,"end":792.912},{"word":"أَحَداٗ","ref":"24:28:5","start":792.912,"end":794.256},{"word":"فَلَا","ref":"24:28:6","start":794.256,"end":795.265},{"word":"تَدْخُلُوهَا","ref":"24:28:7","start":795.265,"end":797.618},{"word":"حَتَّىٰ","ref":"24:28:8","start":797.618,"end":798.29},{"word":"حَتَّىٰ","ref":"24:28:8","start":798.638,"end":799.383},{"word":"يُؤْذَنَ","ref":"24:28:9","start":799.383,"end":800.501},{"word":"لَكُمْۖ","ref":"24:28:10","start":800.501,"end":801.618},{"word":"وَإِن","ref":"24:28:11","start":804.366,"end":805.22},{"word":"قِيلَ","ref":"24:28:12","start":805.22,"end":806.074},{"word":"لَكُمُ","ref":"24:28:13","start":806.074,"end":806.927},{"word":"اُ۪رْجِعُواْ","ref":"24:28:14","start":806.927,"end":808.635},{"word":"فَارْجِعُواْ","ref":"24:28:15","start":808.635,"end":810.627},{"word":"هُوَ","ref":"24:28:16","start":810.627,"end":811.196},{"word":"أَزْكَىٰ","ref":"24:28:17","start":811.196,"end":812.05},{"word":"لَكُمْۖ","ref":"24:28:18","start":815.886,"end":816.805},{"word":"وَاللَّهُ","ref":"24:28:19","start":816.805,"end":818.338},{"word":"بِمَا","ref":"24:28:20","start":818.338,"end":819.257},{"word":"تَعْمَلُونَ","ref":"24:28:21","start":819.257,"end":821.096},{"word":"عَلِيمٞۖ","ref":"24:28:22","start":821.096,"end":822.322}]},{"ayah":29,"words":[{"word":"لَّيْسَ","ref":"24:29:1","start":824.622,"end":825.796},{"word":"عَلَيْكُمْ","ref":"24:29:2","start":825.796,"end":827.753},{"word":"جُنَاحٌ","ref":"24:29:3","start":827.753,"end":829.318},{"word":"أَن","ref":"24:29:4","start":829.318,"end":830.101},{"word":"تَدْخُلُواْ","ref":"24:29:5","start":830.101,"end":832.449},{"word":"بِيُوتاً","ref":"24:29:6","start":832.449,"end":834.406},{"word":"غَيْرَ","ref":"24:29:7","start":834.406,"end":835.58},{"word":"مَسْكُونَةٖ","ref":"24:29:8","start":835.58,"end":837.928},{"word":"فِيهَا","ref":"24:29:9","start":837.928,"end":839.494},{"word":"مَتَٰعٞ","ref":"24:29:10","start":839.494,"end":840.668},{"word":"لَّكُمْۖ","ref":"24:29:11","start":840.668,"end":841.842},{"word":"وَاللَّهُ","ref":"24:29:12","start":843.964,"end":845.831},{"word":"يَعْلَمُ","ref":"24:29:13","start":845.831,"end":847.324},{"word":"مَا","ref":"24:29:14","start":847.324,"end":848.071},{"word":"تُبْدُونَ","ref":"24:29:15","start":848.071,"end":849.938},{"word":"وَمَا","ref":"24:29:16","start":849.938,"end":851.058},{"word":"تَكْتُمُونَۖ","ref":"24:29:17","start":855.9,"end":857.087}]},{"ayah":30,"words":[{"word":"۞","ref":"24:30:1","start":857.087,"end":857.087},{"word":"قُل","ref":"24:30:2","start":857.087,"end":857.483},{"word":"لِّلْمُؤْمِنِينَ","ref":"24:30:3","start":857.483,"end":858.869},{"word":"يَغُضُّواْ","ref":"24:30:4","start":858.869,"end":859.858},{"word":"يَغُضُّواْ","ref":"24:30:4","start":860.06,"end":861.541},{"word":"مِنْ","ref":"24:30:5","start":861.541,"end":862.134},{"word":"أَبْصَٰرِهِمْ","ref":"24:30:6","start":862.134,"end":863.911},{"word":"وَيَحْفَظُواْ","ref":"24:30:7","start":863.911,"end":865.985},{"word":"فُرُوجَهُمْ","ref":"24:30:8","start":865.985,"end":867.762},{"word":"ذَٰلِكَ","ref":"24:30:9","start":869.646,"end":870.938},{"word":"أَزْكَىٰ","ref":"24:30:10","start":870.938,"end":872.23},{"word":"لَهُمْۖ","ref":"24:30:11","start":872.23,"end":873.522},{"word":"إِنَّ","ref":"24:30:12","start":874.958,"end":875.848},{"word":"اَ۬للَّهَ","ref":"24:30:13","start":875.848,"end":877.627},{"word":"خَبِيرُۢ","ref":"24:30:14","start":877.627,"end":879.406},{"word":"بِمَا","ref":"24:30:15","start":879.406,"end":880.741},{"word":"يَصْنَعُونَۖ","ref":"24:30:16","start":880.741,"end":883.41}]},{"ayah":31,"words":[{"word":"وَقُل","ref":"24:31:1","start":886.478,"end":887.608},{"word":"لِّلْمُؤْمِنَٰتِ","ref":"24:31:2","start":887.608,"end":889.867},{"word":"يَغْضُضْنَ","ref":"24:31:3","start":889.867,"end":891.75},{"word":"مِنْ","ref":"24:31:4","start":891.75,"end":892.504},{"word":"أَبْصَٰرِهِنَّ","ref":"24:31:5","start":892.504,"end":894.763},{"word":"وَيَحْفَظْنَ","ref":"24:31:6","start":894.763,"end":897.023},{"word":"فُرُوجَهُنَّۖ","ref":"24:31:7","start":897.023,"end":899.282},{"word":"وَلَا","ref":"24:31:8","start":899.282,"end":900.412},{"word":"يُبْدِينَ","ref":"24:31:9","start":900.412,"end":902.295},{"word":"زِينَتَهُنَّ","ref":"24:31:10","start":902.295,"end":904.555},{"word":"إِلَّا","ref":"24:31:11","start":904.555,"end":905.685},{"word":"مَا","ref":"24:31:12","start":905.685,"end":906.438},{"word":"ظَهَرَ","ref":"24:31:13","start":906.438,"end":907.568},{"word":"مِنْهَاۖ","ref":"24:31:14","start":907.568,"end":909.074},{"word":"وَلْيَضْرِبْنَ","ref":"24:31:15","start":911.164,"end":914.094},{"word":"بِخُمُرِهِنَّ","ref":"24:31:16","start":914.094,"end":916.605},{"word":"عَلَىٰ","ref":"24:31:17","start":916.605,"end":917.443},{"word":"جُيُوبِهِنَّۖ","ref":"24:31:18","start":917.443,"end":919.954},{"word":"وَلَا","ref":"24:31:19","start":921.518,"end":922.531},{"word":"يُبْدِينَ","ref":"24:31:20","start":922.531,"end":924.22},{"word":"زِينَتَهُنَّ","ref":"24:31:21","start":924.22,"end":926.246},{"word":"إِلَّا","ref":"24:31:22","start":926.246,"end":927.259},{"word":"لِبُعُولَتِهِنَّ","ref":"24:31:23","start":927.259,"end":929.961},{"word":"أَوْ","ref":"24:31:24","start":929.961,"end":930.636},{"word":"ءَابَآئِهِنَّ","ref":"24:31:25","start":930.636,"end":933},{"word":"أَوْ","ref":"24:31:26","start":933,"end":933.676},{"word":"ءَابَآءِ","ref":"24:31:27","start":933.676,"end":935.702},{"word":"بُعُولَتِهِنَّ","ref":"24:31:28","start":935.702,"end":938.066},{"word":"أَوْ","ref":"24:31:26","start":946.414,"end":947.465},{"word":"ءَابَآءِ","ref":"24:31:27","start":947.465,"end":950.617},{"word":"بُعُولَتِهِنَّ","ref":"24:31:28","start":950.617,"end":954.295},{"word":"أَوْ","ref":"24:31:29","start":954.295,"end":955.346},{"word":"أَبْنَآئِهِنَّ","ref":"24:31:30","start":965.692,"end":966.362},{"word":"أَوْ","ref":"24:31:31","start":966.362,"end":966.553},{"word":"أَبْنَآءِ","ref":"24:31:32","start":966.553,"end":967.127},{"word":"بُعُولَتِهِنَّ","ref":"24:31:33","start":967.127,"end":967.797},{"word":"أَوْ","ref":"24:31:34","start":967.797,"end":967.988},{"word":"إِخْوَٰنِهِنَّ","ref":"24:31:35","start":967.988,"end":968.562},{"word":"أَوْ","ref":"24:31:34","start":971.118,"end":972.053},{"word":"إِخْوَٰنِهِنَّ","ref":"24:31:35","start":972.053,"end":974.86},{"word":"أَوْ","ref":"24:31:36","start":974.86,"end":975.795},{"word":"بَنِے","ref":"24:31:37","start":975.795,"end":976.731},{"word":"إِخْوَٰنِهِنَّ","ref":"24:31:38","start":976.731,"end":979.537},{"word":"أَوْ","ref":"24:31:39","start":979.537,"end":980.473},{"word":"بَنِے","ref":"24:31:40","start":980.473,"end":981.408},{"word":"أَخَوَٰتِهِنَّ","ref":"24:31:41","start":981.408,"end":984.214},{"word":"أَوْ","ref":"24:31:42","start":984.214,"end":985.15},{"word":"نِسَآئِهِنَّ","ref":"24:31:43","start":985.15,"end":987.956},{"word":"أَوْ","ref":"24:31:44","start":987.956,"end":988.892},{"word":"مَا","ref":"24:31:45","start":988.892,"end":989.827},{"word":"مَلَكَتْ","ref":"24:31:46","start":989.827,"end":991.698},{"word":"أَوْ","ref":"24:31:44","start":994.126,"end":994.783},{"word":"مَا","ref":"24:31:45","start":994.783,"end":995.44},{"word":"مَلَكَتْ","ref":"24:31:46","start":995.44,"end":996.754},{"word":"أَيْمَٰنُهُنَّ","ref":"24:31:47","start":996.956,"end":999.924},{"word":"أَوِ","ref":"24:31:48","start":999.924,"end":1000.914},{"word":"اِ۬لتَّٰبِعِينَ","ref":"24:31:49","start":1001.116,"end":1003.196},{"word":"غَيْرِ","ref":"24:31:50","start":1003.196,"end":1004.087},{"word":"أُوْلِے","ref":"24:31:51","start":1004.087,"end":1004.978},{"word":"اِ۬لْإِرْبَةِ","ref":"24:31:52","start":1004.978,"end":1006.761},{"word":"مِنَ","ref":"24:31:53","start":1006.761,"end":1007.355},{"word":"اَ۬لرِّجَالِ","ref":"24:31:54","start":1007.355,"end":1009.138},{"word":"مِنَ","ref":"24:31:53","start":1011.406,"end":1011.989},{"word":"اَ۬لرِّجَالِ","ref":"24:31:54","start":1011.989,"end":1013.739},{"word":"أَوِ","ref":"24:31:55","start":1013.739,"end":1014.322},{"word":"اِ۬لطِّفْلِ","ref":"24:31:56","start":1014.46,"end":1016.208},{"word":"اِ۬لذِينَ","ref":"24:31:57","start":1016.208,"end":1017.956},{"word":"لَمْ","ref":"24:31:58","start":1017.956,"end":1018.655},{"word":"يَظْهَرُواْ","ref":"24:31:59","start":1018.655,"end":1020.753},{"word":"عَلَىٰ","ref":"24:31:60","start":1020.753,"end":1021.452},{"word":"عَوْرَٰتِ","ref":"24:31:61","start":1021.452,"end":1022.851},{"word":"اِ۬لنِّسَآءِۖ","ref":"24:31:62","start":1022.851,"end":1025.298},{"word":"وَلَا","ref":"24:31:63","start":1027.438,"end":1028.684},{"word":"يَضْرِبْنَ","ref":"24:31:64","start":1028.684,"end":1030.76},{"word":"بِأَرْجُلِهِنَّ","ref":"24:31:65","start":1030.76,"end":1033.666},{"word":"لِيُعْلَمَ","ref":"24:31:66","start":1033.666,"end":1035.742},{"word":"مَا","ref":"24:31:67","start":1035.742,"end":1036.572},{"word":"يُخْفِينَ","ref":"24:31:68","start":1036.572,"end":1038.648},{"word":"مِن","ref":"24:31:69","start":1038.648,"end":1039.479},{"word":"زِينَتِهِنَّۖ","ref":"24:31:70","start":1039.479,"end":1041.97},{"word":"وَتُوبُواْ","ref":"24:31:71","start":1042.972,"end":1045.249},{"word":"إِلَى","ref":"24:31:72","start":1045.249,"end":1046.008},{"word":"اَ۬للَّهِ","ref":"24:31:73","start":1046.008,"end":1047.526},{"word":"جَمِيعاً","ref":"24:31:74","start":1047.526,"end":1049.424},{"word":"أَيُّهَ","ref":"24:31:75","start":1049.424,"end":1050.563},{"word":"اَ۬لْمُؤْمِنُونَ","ref":"24:31:76","start":1050.563,"end":1053.219},{"word":"لَعَلَّكُمْ","ref":"24:31:77","start":1053.219,"end":1055.117},{"word":"تُفْلِحُونَۖ","ref":"24:31:78","start":1055.117,"end":1057.394}]},{"ayah":32,"words":[{"word":"وَأَنكِحُواْ","ref":"24:32:1","start":1058.908,"end":1060.945},{"word":"اُ۬لْأَيَٰمَىٰ","ref":"24:32:2","start":1060.945,"end":1062.4},{"word":"مِنكُمْ","ref":"24:32:3","start":1062.4,"end":1063.564},{"word":"وَالصَّٰلِحِينَ","ref":"24:32:4","start":1063.564,"end":1065.893},{"word":"مِنْ","ref":"24:32:5","start":1065.893,"end":1066.475},{"word":"عِبَادِكُمْ","ref":"24:32:6","start":1066.475,"end":1068.221},{"word":"وَإِمَآئِكُمْۖ","ref":"24:32:7","start":1068.221,"end":1070.258},{"word":"إِنْ","ref":"24:32:8","start":1071.79,"end":1072.409},{"word":"يَّكُونُواْ","ref":"24:32:9","start":1072.409,"end":1074.266},{"word":"فُقَرَآءَ","ref":"24:32:10","start":1074.266,"end":1076.123},{"word":"يُغْنِهِمُ","ref":"24:32:11","start":1076.123,"end":1077.67},{"word":"اُ۬للَّهُ","ref":"24:32:12","start":1077.67,"end":1078.908},{"word":"مِن","ref":"24:32:13","start":1078.908,"end":1079.527},{"word":"فَضْلِهِۦۖ","ref":"24:32:14","start":1079.527,"end":1081.074},{"word":"وَاللَّهُ","ref":"24:32:15","start":1082.172,"end":1083.848},{"word":"وَٰسِعٌ","ref":"24:32:16","start":1083.848,"end":1084.853},{"word":"عَلِيمٞۖ","ref":"24:32:17","start":1084.853,"end":1086.194}]},{"ayah":33,"words":[{"word":"وَلْيَسْتَعْفِفِ","ref":"24:33:1","start":1088.668,"end":1090.741},{"word":"اِ۬لذِينَ","ref":"24:33:2","start":1090.741,"end":1092.037},{"word":"لَا","ref":"24:33:3","start":1092.037,"end":1092.556},{"word":"يَجِدُونَ","ref":"24:33:4","start":1092.556,"end":1093.852},{"word":"نِكَاحاً","ref":"24:33:5","start":1093.852,"end":1095.148},{"word":"حَتَّىٰ","ref":"24:33:6","start":1095.148,"end":1095.666},{"word":"حَتَّىٰ","ref":"24:33:6","start":1095.854,"end":1096.403},{"word":"يُغْنِيَهُمُ","ref":"24:33:7","start":1096.403,"end":1098.052},{"word":"اُ۬للَّهُ","ref":"24:33:8","start":1098.052,"end":1099.151},{"word":"مِن","ref":"24:33:9","start":1099.151,"end":1099.7},{"word":"فَضْلِهِۦۖ","ref":"24:33:10","start":1099.7,"end":1101.074},{"word":"وَالذِينَ","ref":"24:33:11","start":1103.196,"end":1104.93},{"word":"يَبْتَغُونَ","ref":"24:33:12","start":1104.93,"end":1106.664},{"word":"اَ۬لْكِتَٰبَ","ref":"24:33:13","start":1106.664,"end":1108.109},{"word":"مِمَّا","ref":"24:33:14","start":1108.109,"end":1108.976},{"word":"مَلَكَتْ","ref":"24:33:15","start":1108.976,"end":1110.132},{"word":"أَيْمَٰنُكُمْ","ref":"24:33:16","start":1110.132,"end":1111.867},{"word":"فَكَاتِبُوهُمْ","ref":"24:33:17","start":1111.867,"end":1114.179},{"word":"إِنْ","ref":"24:33:18","start":1114.179,"end":1114.757},{"word":"عَلِمْتُمْ","ref":"24:33:19","start":1114.757,"end":1116.202},{"word":"فِيهِمْ","ref":"24:33:20","start":1116.202,"end":1117.358},{"word":"خَيْراٗۖ","ref":"24:33:21","start":1117.358,"end":1118.514},{"word":"وَءَاتُوهُم","ref":"24:33:22","start":1121.02,"end":1123.374},{"word":"مِّن","ref":"24:33:23","start":1123.374,"end":1124.046},{"word":"مَّالِ","ref":"24:33:24","start":1124.046,"end":1125.055},{"word":"اِ۬للَّهِ","ref":"24:33:25","start":1125.055,"end":1126.4},{"word":"اِ۬لذِے","ref":"24:33:26","start":1126.4,"end":1127.409},{"word":"ءَاتَيٰكُمْۖ","ref":"24:33:27","start":1127.409,"end":1129.426},{"word":"وَلَا","ref":"24:33:28","start":1131.63,"end":1132.463},{"word":"تُكْرِهُواْ","ref":"24:33:29","start":1132.463,"end":1134.13},{"word":"فَتَيَٰتِكُمْ","ref":"24:33:30","start":1134.13,"end":1135.797},{"word":"عَلَى","ref":"24:33:31","start":1135.797,"end":1136.352},{"word":"اَ۬لْبِغَآ۟","ref":"24:33:32","start":1136.352,"end":1138.019},{"word":"إِنْ","ref":"24:33:33","start":1138.019,"end":1138.575},{"word":"أَرَدْنَ","ref":"24:33:34","start":1138.575,"end":1139.686},{"word":"تَحَصُّناٗ","ref":"24:33:35","start":1139.686,"end":1141.075},{"word":"لِّتَبْتَغُواْ","ref":"24:33:36","start":1141.075,"end":1143.019},{"word":"عَرَضَ","ref":"24:33:37","start":1143.019,"end":1143.853},{"word":"اَ۬لْحَيَوٰةِ","ref":"24:33:38","start":1143.853,"end":1145.519},{"word":"اِ۬لدُّنْيَاۖ","ref":"24:33:39","start":1145.519,"end":1147.186},{"word":"وَمَنْ","ref":"24:33:40","start":1149.166,"end":1150.343},{"word":"يُّكْرِههُّنَّ","ref":"24:33:41","start":1150.343,"end":1152.697},{"word":"فَإِنَّ","ref":"24:33:42","start":1152.697,"end":1153.874},{"word":"اَ۬للَّهَ","ref":"24:33:43","start":1153.874,"end":1155.443},{"word":"مِنۢ","ref":"24:33:44","start":1155.443,"end":1156.228},{"word":"بَعْدِ","ref":"24:33:45","start":1156.228,"end":1157.405},{"word":"إِكْرَٰهِهِنَّ","ref":"24:33:46","start":1157.405,"end":1159.759},{"word":"غَفُورٞ","ref":"24:33:47","start":1159.759,"end":1161.329},{"word":"رَّحِيمٞۖ","ref":"24:33:48","start":1161.329,"end":1162.898}]},{"ayah":34,"words":[{"word":"وَلَقَدْ","ref":"24:34:1","start":1164.678,"end":1166.053},{"word":"أَنزَلْنَا","ref":"24:34:2","start":1166.053,"end":1168.115},{"word":"إِلَيْكُمْ","ref":"24:34:3","start":1168.115,"end":1169.833},{"word":"ءَايَٰتٖ","ref":"24:34:4","start":1169.833,"end":1171.208},{"word":"مُّبَيَّنَٰتٖ","ref":"24:34:5","start":1171.208,"end":1172.926},{"word":"وَمَثَلاٗ","ref":"24:34:6","start":1172.926,"end":1174.644},{"word":"مِّنَ","ref":"24:34:7","start":1174.644,"end":1175.332},{"word":"اَ۬لذِينَ","ref":"24:34:8","start":1175.332,"end":1177.05},{"word":"خَلَوْاْ","ref":"24:34:9","start":1177.05,"end":1178.425},{"word":"مِن","ref":"24:34:10","start":1178.425,"end":1179.112},{"word":"قَبْلِكُمْ","ref":"24:34:11","start":1179.112,"end":1180.83},{"word":"وَمَوْعِظَةٗ","ref":"24:34:12","start":1180.83,"end":1182.892},{"word":"لِّلْمُتَّقِينَۖ","ref":"24:34:13","start":1182.892,"end":1185.298}]},{"ayah":35,"words":[{"word":"۞","ref":"24:35:1","start":1187.918,"end":1187.918},{"word":"اَ۬للَّهُ","ref":"24:35:2","start":1187.918,"end":1189.044},{"word":"نُورُ","ref":"24:35:3","start":1189.044,"end":1189.888},{"word":"اُ۬لسَّمَٰوَٰتِ","ref":"24:35:4","start":1189.888,"end":1191.577},{"word":"وَالْأَرْضِۖ","ref":"24:35:5","start":1191.577,"end":1193.266},{"word":"مَثَلُ","ref":"24:35:6","start":1194.83,"end":1195.811},{"word":"نُورِهِۦ","ref":"24:35:7","start":1195.811,"end":1197.445},{"word":"كَمِشْكَوٰةٖ","ref":"24:35:8","start":1197.445,"end":1199.406},{"word":"فِيهَا","ref":"24:35:9","start":1199.406,"end":1200.713},{"word":"مِصْبَاحٌۖ","ref":"24:35:10","start":1200.713,"end":1202.347},{"word":"اِ۬لْمِصْبَاحُ","ref":"24:35:11","start":1202.347,"end":1204.635},{"word":"فِے","ref":"24:35:12","start":1204.635,"end":1204.962},{"word":"زُجَاجَةٍۖ","ref":"24:35:13","start":1204.962,"end":1206.596},{"word":"اِ۬لزُّجَاجَةُ","ref":"24:35:14","start":1206.596,"end":1208.884},{"word":"كَأَنَّهَا","ref":"24:35:15","start":1208.884,"end":1210.519},{"word":"كَوْكَبٞ","ref":"24:35:16","start":1210.519,"end":1211.826},{"word":"اِ۬لزُّجَاجَةُ","ref":"24:35:14","start":1213.628,"end":1216.645},{"word":"كَأَنَّهَا","ref":"24:35:15","start":1216.645,"end":1218.799},{"word":"كَوْكَبٞ","ref":"24:35:16","start":1218.799,"end":1220.523},{"word":"دُرِّيّٞ","ref":"24:35:17","start":1220.523,"end":1221.816},{"word":"يُوقَدُ","ref":"24:35:18","start":1221.816,"end":1223.54},{"word":"مِن","ref":"24:35:19","start":1223.54,"end":1224.402},{"word":"شَجَرَةٖ","ref":"24:35:20","start":1224.402,"end":1226.125},{"word":"مُّبَٰرَكَةٖ","ref":"24:35:21","start":1226.125,"end":1228.28},{"word":"زَيْتُونَةٖ","ref":"24:35:22","start":1228.28,"end":1230.866},{"word":"لَّا","ref":"24:35:23","start":1230.866,"end":1231.728},{"word":"شَرْقِيَّةٖ","ref":"24:35:24","start":1231.728,"end":1233.882},{"word":"وَلَا","ref":"24:35:25","start":1233.882,"end":1235.175},{"word":"غَرْبِيَّةٖ","ref":"24:35:26","start":1235.175,"end":1237.33},{"word":"لَّا","ref":"24:35:23","start":1240.174,"end":1240.97},{"word":"شَرْقِيَّةٖ","ref":"24:35:24","start":1240.97,"end":1242.961},{"word":"وَلَا","ref":"24:35:25","start":1242.961,"end":1244.155},{"word":"غَرْبِيَّةٖ","ref":"24:35:26","start":1244.155,"end":1246.146},{"word":"يَكَادُ","ref":"24:35:27","start":1246.146,"end":1247.739},{"word":"زَيْتُهَا","ref":"24:35:28","start":1247.739,"end":1249.73},{"word":"يُضِےٓءُ","ref":"24:35:29","start":1249.73,"end":1251.322},{"word":"وَلَوْ","ref":"24:35:30","start":1251.322,"end":1252.517},{"word":"لَمْ","ref":"24:35:31","start":1252.517,"end":1253.313},{"word":"تَمْسَسْهُ","ref":"24:35:32","start":1253.313,"end":1255.304},{"word":"نَارٞۖ","ref":"24:35:33","start":1255.304,"end":1256.498},{"word":"نُّورٌ","ref":"24:35:34","start":1257.71,"end":1259.008},{"word":"عَلَىٰ","ref":"24:35:35","start":1259.008,"end":1259.873},{"word":"نُورٖۖ","ref":"24:35:36","start":1259.873,"end":1261.17},{"word":"يَهْدِے","ref":"24:35:37","start":1262.19,"end":1263.285},{"word":"اِ۬للَّهُ","ref":"24:35:38","start":1263.285,"end":1264.745},{"word":"لِنُورِهِۦ","ref":"24:35:39","start":1264.745,"end":1266.935},{"word":"مَنْ","ref":"24:35:40","start":1266.935,"end":1267.665},{"word":"يَّشَآءُۖ","ref":"24:35:41","start":1267.665,"end":1269.49},{"word":"وَيَضْرِبُ","ref":"24:35:42","start":1271.612,"end":1273.138},{"word":"اُ۬للَّهُ","ref":"24:35:43","start":1273.138,"end":1274.358},{"word":"اُ۬لْأَمْثَٰلَ","ref":"24:35:44","start":1274.358,"end":1276.188},{"word":"لِلنَّاسِۖ","ref":"24:35:45","start":1276.188,"end":1277.714},{"word":"وَاللَّهُ","ref":"24:35:46","start":1278.364,"end":1280.406},{"word":"بِكُلِّ","ref":"24:35:47","start":1280.406,"end":1281.631},{"word":"شَےْءٍ","ref":"24:35:48","start":1281.631,"end":1282.448},{"word":"عَلِيمٞۖ","ref":"24:35:49","start":1282.448,"end":1284.082}]},{"ayah":36,"words":[{"word":"فِے","ref":"24:36:1","start":1286.638,"end":1286.951},{"word":"بِيُوتٍ","ref":"24:36:2","start":1286.951,"end":1288.204},{"word":"أَذِنَ","ref":"24:36:3","start":1288.204,"end":1289.143},{"word":"اَ۬للَّهُ","ref":"24:36:4","start":1289.143,"end":1290.395},{"word":"أَن","ref":"24:36:5","start":1290.395,"end":1291.022},{"word":"تُرْفَعَ","ref":"24:36:6","start":1291.022,"end":1292.274},{"word":"وَيُذْكَرَ","ref":"24:36:7","start":1292.274,"end":1293.84},{"word":"فِيهَا","ref":"24:36:8","start":1293.84,"end":1295.092},{"word":"اَ۪سْمُهُۥ","ref":"24:36:9","start":1295.092,"end":1296.658},{"word":"يُسَبِّحُ","ref":"24:36:10","start":1298.886,"end":1300.161},{"word":"لَهُۥ","ref":"24:36:11","start":1300.161,"end":1301.117},{"word":"فِيهَا","ref":"24:36:12","start":1301.117,"end":1302.392},{"word":"بِالْغُدُوِّ","ref":"24:36:13","start":1302.392,"end":1304.304},{"word":"وَالْأٓصَالِ","ref":"24:36:14","start":1304.304,"end":1306.854},{"word":"رِجَالٞ","ref":"24:36:15","start":1306.854,"end":1308.129},{"word":"لَّا","ref":"24:36:16","start":1308.129,"end":1308.767},{"word":"تُلْهِيهِمْ","ref":"24:36:17","start":1308.767,"end":1310.679},{"word":"تِجَٰرَةٞ","ref":"24:36:18","start":1310.679,"end":1311.954},{"word":"رِجَالٞ","ref":"24:36:15","start":1314.118,"end":1315.481},{"word":"لَّا","ref":"24:36:16","start":1315.481,"end":1316.163},{"word":"تُلْهِيهِمْ","ref":"24:36:17","start":1316.163,"end":1318.208},{"word":"تِجَٰرَةٞ","ref":"24:36:18","start":1318.208,"end":1319.572},{"word":"وَلَا","ref":"24:36:19","start":1319.572,"end":1320.594},{"word":"بَيْعٌ","ref":"24:36:20","start":1320.594,"end":1321.617},{"word":"عَن","ref":"24:36:21","start":1321.617,"end":1322.299},{"word":"ذِكْرِ","ref":"24:36:22","start":1322.299,"end":1323.321},{"word":"اِ۬للَّهِ","ref":"24:36:23","start":1323.321,"end":1324.685},{"word":"وَإِقَامِ","ref":"24:36:24","start":1324.685,"end":1326.389},{"word":"اِ۬لصَّلَوٰةِ","ref":"24:36:25","start":1326.389,"end":1328.434},{"word":"وَإِيتَآءِ","ref":"24:36:26","start":1328.434,"end":1330.82},{"word":"اِ۬لزَّكَوٰةِۖ","ref":"24:36:27","start":1330.82,"end":1332.865},{"word":"يَخَافُونَ","ref":"24:36:28","start":1332.865,"end":1334.911},{"word":"يَوْماٗ","ref":"24:36:29","start":1334.911,"end":1336.274},{"word":"يَخَافُونَ","ref":"24:36:28","start":1339.228,"end":1341.208},{"word":"يَوْماٗ","ref":"24:36:29","start":1341.208,"end":1342.528},{"word":"تَتَقَلَّبُ","ref":"24:36:30","start":1342.528,"end":1344.178},{"word":"فِيهِ","ref":"24:36:31","start":1344.178,"end":1345.168},{"word":"اِ۬لْقُلُوبُ","ref":"24:36:32","start":1345.168,"end":1347.148},{"word":"وَالْأَبْصَٰرُ","ref":"24:36:33","start":1347.148,"end":1349.458}]},{"ayah":37,"words":[{"word":"لِيَجْزِيَهُمُ","ref":"24:37:1","start":1351.644,"end":1353.77},{"word":"اُ۬للَّهُ","ref":"24:37:2","start":1353.77,"end":1354.985},{"word":"أَحْسَنَ","ref":"24:37:3","start":1354.985,"end":1356.2},{"word":"مَا","ref":"24:37:4","start":1356.2,"end":1356.807},{"word":"عَمِلُواْ","ref":"24:37:5","start":1356.807,"end":1358.326},{"word":"وَيَزِيدَهُم","ref":"24:37:6","start":1358.326,"end":1360.452},{"word":"مِّن","ref":"24:37:7","start":1360.452,"end":1361.059},{"word":"فَضْلِهِۦۖ","ref":"24:37:8","start":1361.059,"end":1362.578},{"word":"وَاللَّهُ","ref":"24:37:9","start":1364.668,"end":1366.499},{"word":"يَرْزُقُ","ref":"24:37:10","start":1366.499,"end":1367.964},{"word":"مَنْ","ref":"24:37:11","start":1367.964,"end":1368.697},{"word":"يَّشَآءُ","ref":"24:37:12","start":1368.697,"end":1370.528},{"word":"بِغَيْرِ","ref":"24:37:13","start":1370.528,"end":1371.993},{"word":"حِسَابٖۖ","ref":"24:37:14","start":1371.993,"end":1373.458}]},{"ayah":38,"words":[{"word":"وَالذِينَ","ref":"24:38:1","start":1376.636,"end":1378.738},{"word":"كَفَرُواْ","ref":"24:38:2","start":1378.738,"end":1380.49},{"word":"أَعْمَٰلُهُمْ","ref":"24:38:3","start":1380.49,"end":1382.592},{"word":"كَسَرَابِۢ","ref":"24:38:4","start":1382.592,"end":1384.344},{"word":"بِقِيعَةٖ","ref":"24:38:5","start":1384.344,"end":1386.096},{"word":"يَحْسِبُهُ","ref":"24:38:6","start":1386.096,"end":1387.847},{"word":"اُ۬لظَّمْـَٔانُ","ref":"24:38:7","start":1387.847,"end":1390.3},{"word":"مَآءً","ref":"24:38:8","start":1390.3,"end":1391.701},{"word":"حَتَّىٰ","ref":"24:38:9","start":1391.701,"end":1392.402},{"word":"إِذَا","ref":"24:38:10","start":1392.718,"end":1393.871},{"word":"جَآءَهُۥ","ref":"24:38:11","start":1393.871,"end":1396.176},{"word":"لَمْ","ref":"24:38:12","start":1396.176,"end":1396.944},{"word":"يَجِدْهُ","ref":"24:38:13","start":1396.944,"end":1398.481},{"word":"شَئْاٗ","ref":"24:38:14","start":1398.481,"end":1400.018},{"word":"حَتَّىٰ","ref":"24:38:9","start":1404.974,"end":1405.639},{"word":"إِذَا","ref":"24:38:10","start":1405.639,"end":1406.636},{"word":"جَآءَهُۥ","ref":"24:38:11","start":1406.636,"end":1408.631},{"word":"لَمْ","ref":"24:38:12","start":1408.631,"end":1409.295},{"word":"يَجِدْهُ","ref":"24:38:13","start":1409.295,"end":1410.625},{"word":"شَئْاٗ","ref":"24:38:14","start":1410.625,"end":1411.955},{"word":"وَوَجَدَ","ref":"24:38:15","start":1411.955,"end":1413.284},{"word":"اَ۬للَّهَ","ref":"24:38:16","start":1413.284,"end":1414.614},{"word":"عِندَهُۥ","ref":"24:38:17","start":1414.614,"end":1416.276},{"word":"فَوَفَّيٰهُ","ref":"24:38:18","start":1416.276,"end":1417.938},{"word":"فَوَفَّيٰهُ","ref":"24:38:18","start":1418.108,"end":1419.223},{"word":"حِسَابَهُۥۖ","ref":"24:38:19","start":1419.223,"end":1420.562},{"word":"وَاللَّهُ","ref":"24:38:20","start":1422.716,"end":1424.313},{"word":"سَرِيعُ","ref":"24:38:21","start":1424.313,"end":1425.59},{"word":"اُ۬لْحِسَابِۖ","ref":"24:38:22","start":1425.59,"end":1427.506}]},{"ayah":39,"words":[{"word":"أَوْ","ref":"24:39:1","start":1430.542,"end":1431.411},{"word":"كَظُلُمَٰتٖ","ref":"24:39:2","start":1431.411,"end":1433.585},{"word":"فِے","ref":"24:39:3","start":1433.585,"end":1434.02},{"word":"بَحْرٖ","ref":"24:39:4","start":1434.02,"end":1435.324},{"word":"لُّجِّيّٖ","ref":"24:39:5","start":1435.324,"end":1436.628},{"word":"يَغْشَيٰهُ","ref":"24:39:6","start":1436.628,"end":1438.801},{"word":"مَوْجٞ","ref":"24:39:7","start":1438.801,"end":1440.105},{"word":"مِّن","ref":"24:39:8","start":1440.105,"end":1440.975},{"word":"فَوْقِهِۦ","ref":"24:39:9","start":1440.975,"end":1443.148},{"word":"مَوْجٞ","ref":"24:39:10","start":1443.148,"end":1444.452},{"word":"مِّن","ref":"24:39:11","start":1444.452,"end":1445.322},{"word":"فَوْقِهِۦ","ref":"24:39:12","start":1445.322,"end":1447.495},{"word":"سَحَابٞۖ","ref":"24:39:13","start":1447.495,"end":1449.234},{"word":"ظُلُمَٰتُۢ","ref":"24:39:14","start":1452.518,"end":1453.888},{"word":"بَعْضُهَا","ref":"24:39:15","start":1453.888,"end":1455.601},{"word":"فَوْقَ","ref":"24:39:16","start":1455.601,"end":1456.629},{"word":"بَعْضٍۖ","ref":"24:39:17","start":1456.629,"end":1457.656},{"word":"إِذَا","ref":"24:39:18","start":1457.656,"end":1458.684},{"word":"أَخْرَجَ","ref":"24:39:19","start":1458.684,"end":1460.054},{"word":"يَدَهُۥ","ref":"24:39:20","start":1460.054,"end":1461.424},{"word":"لَمْ","ref":"24:39:21","start":1461.424,"end":1462.11},{"word":"يَكَدْ","ref":"24:39:22","start":1462.11,"end":1463.137},{"word":"يَرَيٰهَاۖ","ref":"24:39:23","start":1463.137,"end":1464.85},{"word":"وَمَن","ref":"24:39:24","start":1467.086,"end":1468.068},{"word":"لَّمْ","ref":"24:39:25","start":1468.068,"end":1468.723},{"word":"يَجْعَلِ","ref":"24:39:26","start":1468.723,"end":1470.032},{"word":"اِ۬للَّهُ","ref":"24:39:27","start":1470.032,"end":1471.342},{"word":"لَهُۥ","ref":"24:39:28","start":1471.342,"end":1472.324},{"word":"نُوراٗ","ref":"24:39:29","start":1472.324,"end":1473.633},{"word":"فَمَا","ref":"24:39:30","start":1473.633,"end":1474.615},{"word":"لَهُۥ","ref":"24:39:31","start":1474.615,"end":1475.597},{"word":"مِن","ref":"24:39:32","start":1475.597,"end":1476.252},{"word":"نُّورٍۖ","ref":"24:39:33","start":1476.252,"end":1477.234}]},{"ayah":40,"words":[{"word":"أَلَمْ","ref":"24:40:1","start":1480.526,"end":1481.579},{"word":"تَرَ","ref":"24:40:2","start":1481.579,"end":1482.282},{"word":"أَنَّ","ref":"24:40:3","start":1482.282,"end":1482.984},{"word":"اَ۬للَّهَ","ref":"24:40:4","start":1482.984,"end":1484.389},{"word":"يُسَبِّحُ","ref":"24:40:5","start":1484.389,"end":1485.793},{"word":"لَهُۥ","ref":"24:40:6","start":1485.793,"end":1486.847},{"word":"مَن","ref":"24:40:7","start":1486.847,"end":1487.549},{"word":"فِے","ref":"24:40:8","start":1487.549,"end":1487.9},{"word":"اِ۬لسَّمَٰوَٰتِ","ref":"24:40:9","start":1487.9,"end":1490.007},{"word":"وَالْأَرْضِ","ref":"24:40:10","start":1490.007,"end":1492.114},{"word":"وَالطَّيْرُ","ref":"24:40:11","start":1499.836,"end":1501.234},{"word":"صَٰٓفَّٰتٖۖ","ref":"24:40:12","start":1501.234,"end":1502.166},{"word":"كُلّٞ","ref":"24:40:13","start":1502.166,"end":1502.632},{"word":"قَدْ","ref":"24:40:14","start":1502.632,"end":1503.098},{"word":"عَلِمَ","ref":"24:40:15","start":1503.098,"end":1503.796},{"word":"صَلَاتَهُۥ","ref":"24:40:16","start":1503.796,"end":1505.194},{"word":"وَتَسْبِيحَهُۥۖ","ref":"24:40:17","start":1505.194,"end":1507.058},{"word":"وَاللَّهُ","ref":"24:40:18","start":1508.476,"end":1510.26},{"word":"عَلِيمُۢ","ref":"24:40:19","start":1510.26,"end":1511.687},{"word":"بِمَا","ref":"24:40:20","start":1511.687,"end":1512.757},{"word":"يَفْعَلُونَۖ","ref":"24:40:21","start":1512.757,"end":1514.898}]},{"ayah":41,"words":[{"word":"وَلِلهِ","ref":"24:41:1","start":1517.158,"end":1518.454},{"word":"مُلْكُ","ref":"24:41:2","start":1518.454,"end":1519.426},{"word":"اُ۬لسَّمَٰوَٰتِ","ref":"24:41:3","start":1519.426,"end":1521.37},{"word":"وَالْأَرْضِۖ","ref":"24:41:4","start":1521.37,"end":1523.314},{"word":"وَإِلَى","ref":"24:41:5","start":1525.038,"end":1525.977},{"word":"اَ۬للَّهِ","ref":"24:41:6","start":1525.977,"end":1527.228},{"word":"اِ۬لْمَصِيرُۖ","ref":"24:41:7","start":1527.228,"end":1529.106}]},{"ayah":42,"words":[{"word":"۞","ref":"24:42:1","start":1532.238,"end":1532.238},{"word":"أَلَمْ","ref":"24:42:2","start":1532.238,"end":1533.397},{"word":"تَرَ","ref":"24:42:3","start":1533.397,"end":1534.17},{"word":"أَنَّ","ref":"24:42:4","start":1534.17,"end":1534.943},{"word":"اَ۬للَّهَ","ref":"24:42:5","start":1534.943,"end":1536.488},{"word":"يُزْجِے","ref":"24:42:6","start":1536.488,"end":1537.647},{"word":"سَحَاباٗ","ref":"24:42:7","start":1537.647,"end":1539.579},{"word":"ثُمَّ","ref":"24:42:8","start":1539.579,"end":1540.352},{"word":"يُؤَلِّفُ","ref":"24:42:9","start":1540.352,"end":1541.511},{"word":"بَيْنَهُۥ","ref":"24:42:10","start":1541.511,"end":1543.443},{"word":"ثُمَّ","ref":"24:42:11","start":1543.443,"end":1544.216},{"word":"يَجْعَلُهُۥ","ref":"24:42:12","start":1544.216,"end":1546.534},{"word":"رُكَاماٗ","ref":"24:42:13","start":1546.534,"end":1548.466},{"word":"ثُمَّ","ref":"24:42:11","start":1550.926,"end":1551.56},{"word":"يَجْعَلُهُۥ","ref":"24:42:12","start":1551.56,"end":1553.463},{"word":"رُكَاماٗ","ref":"24:42:13","start":1553.463,"end":1555.049},{"word":"فَتَرَى","ref":"24:42:14","start":1555.049,"end":1556},{"word":"اَ۬لْوَدْقَ","ref":"24:42:15","start":1556,"end":1557.586},{"word":"يَخْرُجُ","ref":"24:42:16","start":1557.586,"end":1558.854},{"word":"مِنْ","ref":"24:42:17","start":1558.854,"end":1559.488},{"word":"خِلَٰلِهِۦۖ","ref":"24:42:18","start":1559.488,"end":1561.074},{"word":"وَيُنَزِّلُ","ref":"24:42:19","start":1563.196,"end":1565.086},{"word":"مِنَ","ref":"24:42:20","start":1565.086,"end":1565.842},{"word":"اَ۬لسَّمَآءِ","ref":"24:42:21","start":1565.842,"end":1568.487},{"word":"مِن","ref":"24:42:22","start":1568.487,"end":1569.243},{"word":"جِبَالٖ","ref":"24:42:23","start":1569.243,"end":1570.755},{"word":"فِيهَا","ref":"24:42:24","start":1570.755,"end":1572.267},{"word":"مِنۢ","ref":"24:42:25","start":1572.267,"end":1573.023},{"word":"بَرَدٖ","ref":"24:42:26","start":1573.023,"end":1574.157},{"word":"فَيُصِيبُ","ref":"24:42:27","start":1574.157,"end":1576.046},{"word":"بِهِۦ","ref":"24:42:28","start":1576.046,"end":1577.18},{"word":"مَنْ","ref":"24:42:29","start":1577.18,"end":1577.936},{"word":"يَّشَآءُ","ref":"24:42:30","start":1577.936,"end":1579.826},{"word":"فَيُصِيبُ","ref":"24:42:27","start":1581.852,"end":1583.884},{"word":"بِهِۦ","ref":"24:42:28","start":1583.884,"end":1585.103},{"word":"مَنْ","ref":"24:42:29","start":1585.103,"end":1585.916},{"word":"يَّشَآءُ","ref":"24:42:30","start":1585.916,"end":1587.948},{"word":"وَيَصْرِفُهُۥ","ref":"24:42:31","start":1587.948,"end":1590.793},{"word":"عَن","ref":"24:42:32","start":1590.793,"end":1591.605},{"word":"مَّنْ","ref":"24:42:33","start":1591.605,"end":1592.418},{"word":"يَّشَآءُۖ","ref":"24:42:34","start":1592.418,"end":1594.45},{"word":"يَكَادُ","ref":"24:42:35","start":1595.974,"end":1597.251},{"word":"سَنَا","ref":"24:42:36","start":1597.251,"end":1598.208},{"word":"بَرْقِهِۦ","ref":"24:42:37","start":1598.208,"end":1599.804},{"word":"يَذْهَبُ","ref":"24:42:38","start":1599.804,"end":1601.08},{"word":"بِالْأَبْصَٰرِۖ","ref":"24:42:39","start":1601.08,"end":1603.314},{"word":"يُقَلِّبُ","ref":"24:42:40","start":1604.998,"end":1606.341},{"word":"اُ۬للَّهُ","ref":"24:42:41","start":1606.341,"end":1607.684},{"word":"اُ۬ليْلَ","ref":"24:42:42","start":1607.684,"end":1609.027},{"word":"وَالنَّهَارَۖ","ref":"24:42:43","start":1609.027,"end":1611.378},{"word":"إِنَّ","ref":"24:42:44","start":1612.622,"end":1613.375},{"word":"فِے","ref":"24:42:45","start":1613.375,"end":1613.752},{"word":"ذَٰلِكَ","ref":"24:42:46","start":1613.752,"end":1614.881},{"word":"لَعِبْرَةٗ","ref":"24:42:47","start":1614.881,"end":1616.764},{"word":"لِّأُوْلِے","ref":"24:42:48","start":1616.764,"end":1618.271},{"word":"اِ۬لْأَبْصَٰرِۖ","ref":"24:42:49","start":1618.271,"end":1620.53}]},{"ayah":43,"words":[{"word":"وَاللَّهُ","ref":"24:43:1","start":1622.844,"end":1626.151},{"word":"خَلَقَ","ref":"24:43:2","start":1626.151,"end":1628.135},{"word":"كُلَّ","ref":"24:43:3","start":1628.135,"end":1629.458},{"word":"دَآبَّةٖ","ref":"24:43:4","start":1629.564,"end":1631.698},{"word":"مِّن","ref":"24:43:5","start":1631.698,"end":1632.551},{"word":"مَّآءٖۖ","ref":"24:43:6","start":1632.551,"end":1634.258},{"word":"فَمِنْهُم","ref":"24:43:7","start":1636.508,"end":1638.359},{"word":"مَّنْ","ref":"24:43:8","start":1638.359,"end":1639.1},{"word":"يَّمْشِے","ref":"24:43:9","start":1639.1,"end":1640.21},{"word":"عَلَىٰ","ref":"24:43:10","start":1640.21,"end":1640.951},{"word":"بَطْنِهِۦۖ","ref":"24:43:11","start":1640.951,"end":1642.802},{"word":"وَمِنْهُم","ref":"24:43:12","start":1644.348,"end":1646.5},{"word":"مَّنْ","ref":"24:43:13","start":1646.5,"end":1647.361},{"word":"يَّمْشِے","ref":"24:43:14","start":1647.361,"end":1648.653},{"word":"عَلَىٰ","ref":"24:43:15","start":1648.653,"end":1649.514},{"word":"رِجْلَيْنِۖ","ref":"24:43:16","start":1649.514,"end":1651.666},{"word":"وَمِنْهُم","ref":"24:43:17","start":1653.18,"end":1655.337},{"word":"مَّنْ","ref":"24:43:18","start":1655.337,"end":1656.2},{"word":"يَّمْشِے","ref":"24:43:19","start":1656.2,"end":1657.494},{"word":"عَلَىٰ","ref":"24:43:20","start":1657.494,"end":1658.357},{"word":"أَرْبَعٖۖ","ref":"24:43:21","start":1658.357,"end":1660.082},{"word":"يَخْلُقُ","ref":"24:43:22","start":1662.342,"end":1663.813},{"word":"اُ۬للَّهُ","ref":"24:43:23","start":1663.813,"end":1665.284},{"word":"مَا","ref":"24:43:24","start":1665.284,"end":1666.019},{"word":"يَشَآءُۖ","ref":"24:43:25","start":1666.019,"end":1667.858},{"word":"اِ۪نَّ","ref":"24:43:26","start":1669.39,"end":1670.415},{"word":"اَ۬للَّهَ","ref":"24:43:27","start":1670.415,"end":1672.464},{"word":"عَلَىٰ","ref":"24:43:28","start":1672.464,"end":1673.488},{"word":"كُلِّ","ref":"24:43:29","start":1673.488,"end":1674.513},{"word":"شَےْءٖ","ref":"24:43:30","start":1674.513,"end":1675.537},{"word":"قَدِيرٞۖ","ref":"24:43:31","start":1675.537,"end":1677.586}]},{"ayah":44,"words":[{"word":"لَّقَدْ","ref":"24:44:1","start":1679.694,"end":1681.012},{"word":"أَنزَلْنَا","ref":"24:44:2","start":1681.012,"end":1683.648},{"word":"ءَايَٰتٖ","ref":"24:44:3","start":1683.648,"end":1685.405},{"word":"مُّبَيَّنَٰتٖۖ","ref":"24:44:4","start":1685.405,"end":1687.602},{"word":"وَاللَّهُ","ref":"24:44:5","start":1689.244,"end":1691.562},{"word":"يَهْدِے","ref":"24:44:6","start":1691.562,"end":1692.953},{"word":"مَنْ","ref":"24:44:7","start":1692.953,"end":1693.88},{"word":"يَّشَآءُ","ref":"24:44:8","start":1693.88,"end":1696.198},{"word":"اِ۪لَىٰ","ref":"24:44:9","start":1696.198,"end":1697.125},{"word":"صِرَٰطٖ","ref":"24:44:10","start":1697.125,"end":1698.516},{"word":"مُّسْتَقِيمٖۖ","ref":"24:44:11","start":1698.516,"end":1701.298}]},{"ayah":45,"words":[{"word":"وَيَقُولُونَ","ref":"24:45:1","start":1704.412,"end":1707.044},{"word":"ءَامَنَّا","ref":"24:45:2","start":1707.044,"end":1708.924},{"word":"بِاللَّهِ","ref":"24:45:3","start":1708.924,"end":1710.803},{"word":"وَبِالرَّسُولِ","ref":"24:45:4","start":1710.803,"end":1713.811},{"word":"وَأَطَعْنَا","ref":"24:45:5","start":1713.811,"end":1716.067},{"word":"ثُمَّ","ref":"24:45:6","start":1716.067,"end":1716.819},{"word":"يَتَوَلَّىٰ","ref":"24:45:7","start":1716.819,"end":1718.323},{"word":"فَرِيقٞ","ref":"24:45:8","start":1718.323,"end":1719.826},{"word":"مِّنْهُم","ref":"24:45:9","start":1719.826,"end":1721.33},{"word":"مِّنۢ","ref":"24:45:10","start":1721.33,"end":1722.082},{"word":"بَعْدِ","ref":"24:45:11","start":1722.082,"end":1723.21},{"word":"ذَٰلِكَۖ","ref":"24:45:12","start":1723.21,"end":1724.338},{"word":"وَمَا","ref":"24:45:13","start":1727.022,"end":1728.235},{"word":"أُوْلَٰٓئِكَ","ref":"24:45:14","start":1728.235,"end":1730.256},{"word":"بِالْمُؤْمِنِينَۖ","ref":"24:45:15","start":1730.256,"end":1733.49}]},{"ayah":46,"words":[{"word":"وَإِذَا","ref":"24:46:1","start":1736.262,"end":1737.575},{"word":"دُعُواْ","ref":"24:46:2","start":1737.575,"end":1738.888},{"word":"إِلَى","ref":"24:46:3","start":1738.888,"end":1739.545},{"word":"اَ۬للَّهِ","ref":"24:46:4","start":1739.545,"end":1740.858},{"word":"وَرَسُولِهِۦ","ref":"24:46:5","start":1740.858,"end":1743.155},{"word":"لِيَحْكُمَ","ref":"24:46:6","start":1743.155,"end":1744.797},{"word":"بَيْنَهُمْ","ref":"24:46:7","start":1744.797,"end":1746.438},{"word":"إِذَا","ref":"24:46:8","start":1746.438,"end":1747.423},{"word":"فَرِيقٞ","ref":"24:46:9","start":1747.423,"end":1748.736},{"word":"مِّنْهُم","ref":"24:46:10","start":1748.736,"end":1750.049},{"word":"مُّعْرِضُونَۖ","ref":"24:46:11","start":1750.049,"end":1752.018}]},{"ayah":47,"words":[{"word":"وَإِنْ","ref":"24:47:1","start":1754.638,"end":1755.54},{"word":"يَّكُن","ref":"24:47:2","start":1755.54,"end":1756.442},{"word":"لَّهُمُ","ref":"24:47:3","start":1756.442,"end":1757.344},{"word":"اُ۬لْحَقُّ","ref":"24:47:4","start":1757.344,"end":1758.546},{"word":"يَأْتُواْ","ref":"24:47:5","start":1759.676,"end":1760.974},{"word":"إِلَيْهِ","ref":"24:47:6","start":1760.974,"end":1762.012},{"word":"مُذْعِنِينَۖ","ref":"24:47:7","start":1762.012,"end":1763.57}]},{"ayah":48,"words":[{"word":"أَفِے","ref":"24:48:1","start":1766.286,"end":1766.944},{"word":"قُلُوبِهِم","ref":"24:48:2","start":1766.944,"end":1768.918},{"word":"مَّرَضٌ","ref":"24:48:3","start":1768.918,"end":1769.905},{"word":"أَمِ","ref":"24:48:4","start":1769.905,"end":1770.564},{"word":"اِ۪رْتَابُواْ","ref":"24:48:5","start":1770.564,"end":1772.867},{"word":"أَمْ","ref":"24:48:6","start":1772.867,"end":1773.525},{"word":"يَخَافُونَ","ref":"24:48:7","start":1773.525,"end":1775.499},{"word":"أَنْ","ref":"24:48:8","start":1775.499,"end":1776.157},{"word":"يَّحِيفَ","ref":"24:48:9","start":1776.157,"end":1777.473},{"word":"اَ۬للَّهُ","ref":"24:48:10","start":1777.473,"end":1778.79},{"word":"عَلَيْهِمْ","ref":"24:48:11","start":1778.79,"end":1780.435},{"word":"وَرَسُولُهُۥۖ","ref":"24:48:12","start":1780.435,"end":1782.738},{"word":"بَلْ","ref":"24:48:13","start":1785.006,"end":1785.855},{"word":"أُوْلَٰٓئِكَ","ref":"24:48:14","start":1785.855,"end":1787.976},{"word":"هُمُ","ref":"24:48:15","start":1787.976,"end":1788.824},{"word":"اُ۬لظَّٰلِمُونَۖ","ref":"24:48:16","start":1788.824,"end":1791.794}]},{"ayah":49,"words":[{"word":"إِنَّمَا","ref":"24:49:1","start":1794.406,"end":1795.698},{"word":"كَانَ","ref":"24:49:2","start":1795.698,"end":1796.668},{"word":"قَوْلَ","ref":"24:49:3","start":1796.668,"end":1797.637},{"word":"اَ۬لْمُؤْمِنِينَ","ref":"24:49:4","start":1797.637,"end":1799.899},{"word":"إِذَا","ref":"24:49:5","start":1799.899,"end":1800.868},{"word":"دُعُواْ","ref":"24:49:6","start":1800.868,"end":1802.16},{"word":"إِلَى","ref":"24:49:7","start":1802.16,"end":1802.806},{"word":"اَ۬للَّهِ","ref":"24:49:8","start":1802.806,"end":1804.099},{"word":"وَرَسُولِهِۦ","ref":"24:49:9","start":1804.099,"end":1806.36},{"word":"لِيَحْكُمَ","ref":"24:49:10","start":1806.36,"end":1807.976},{"word":"بَيْنَهُمْ","ref":"24:49:11","start":1807.976,"end":1809.591},{"word":"أَنْ","ref":"24:49:12","start":1809.591,"end":1810.237},{"word":"يَّقُولُواْ","ref":"24:49:13","start":1810.237,"end":1812.176},{"word":"سَمِعْنَا","ref":"24:49:14","start":1812.176,"end":1813.791},{"word":"وَأَطَعْنَاۖ","ref":"24:49:15","start":1813.791,"end":1815.73},{"word":"وَأُوْلَٰٓئِكَ","ref":"24:49:16","start":1819.1,"end":1821.616},{"word":"هُمُ","ref":"24:49:17","start":1821.616,"end":1822.455},{"word":"اُ۬لْمُفْلِحُونَۖ","ref":"24:49:18","start":1822.455,"end":1825.81}]},{"ayah":50,"words":[{"word":"وَمَنْ","ref":"24:50:1","start":1828.366,"end":1829.262},{"word":"يُّطِعِ","ref":"24:50:2","start":1829.262,"end":1830.159},{"word":"اِ۬للَّهَ","ref":"24:50:3","start":1830.159,"end":1831.354},{"word":"وَرَسُولَهُۥ","ref":"24:50:4","start":1831.354,"end":1833.446},{"word":"وَيَخْشَ","ref":"24:50:5","start":1833.446,"end":1834.641},{"word":"اَ۬للَّهَ","ref":"24:50:6","start":1834.641,"end":1835.836},{"word":"وَيَتَّقِهِ","ref":"24:50:7","start":1835.836,"end":1837.33},{"word":"فَأُوْلَٰٓئِكَ","ref":"24:50:8","start":1837.5,"end":1840.892},{"word":"هُمُ","ref":"24:50:9","start":1840.892,"end":1842.023},{"word":"اُ۬لْفَآئِزُونَۖ","ref":"24:50:10","start":1842.023,"end":1846.546}]},{"ayah":51,"words":[{"word":"۞","ref":"24:51:1","start":1848.398,"end":1848.398},{"word":"وَأَقْسَمُواْ","ref":"24:51:2","start":1848.398,"end":1850.741},{"word":"بِاللَّهِ","ref":"24:51:3","start":1850.741,"end":1852.415},{"word":"جَهْدَ","ref":"24:51:4","start":1852.415,"end":1853.419},{"word":"أَيْمَٰنِهِمْ","ref":"24:51:5","start":1853.419,"end":1855.428},{"word":"لَئِنْ","ref":"24:51:6","start":1855.428,"end":1856.097},{"word":"أَمَرْتَهُمْ","ref":"24:51:7","start":1856.097,"end":1858.106},{"word":"لَيَخْرُجُنَّۖ","ref":"24:51:8","start":1858.106,"end":1860.114},{"word":"قُل","ref":"24:51:9","start":1861.326,"end":1861.941},{"word":"لَّا","ref":"24:51:10","start":1861.941,"end":1862.556},{"word":"تُقْسِمُواْۖ","ref":"24:51:11","start":1862.556,"end":1864.402},{"word":"طَاعَةٞ","ref":"24:51:12","start":1865.67,"end":1867.326},{"word":"مَّعْرُوفَةٌۖ","ref":"24:51:13","start":1867.326,"end":1869.81},{"word":"إِنَّ","ref":"24:51:14","start":1871.086,"end":1871.942},{"word":"اَ۬للَّهَ","ref":"24:51:15","start":1871.942,"end":1873.654},{"word":"خَبِيرُۢ","ref":"24:51:16","start":1873.654,"end":1875.366},{"word":"بِمَا","ref":"24:51:17","start":1875.366,"end":1876.65},{"word":"تَعْمَلُونَۖ","ref":"24:51:18","start":1876.65,"end":1879.218}]},{"ayah":52,"words":[{"word":"قُلْ","ref":"24:52:1","start":1880.654,"end":1881.212},{"word":"أَطِيعُواْ","ref":"24:52:2","start":1881.212,"end":1882.888},{"word":"اُ۬للَّهَ","ref":"24:52:3","start":1882.888,"end":1884.004},{"word":"وَأَطِيعُواْ","ref":"24:52:4","start":1884.004,"end":1885.959},{"word":"اُ۬لرَّسُولَۖ","ref":"24:52:5","start":1885.959,"end":1887.634},{"word":"فَإِن","ref":"24:52:6","start":1889.646,"end":1890.839},{"word":"تَوَلَّوْاْ","ref":"24:52:7","start":1890.839,"end":1892.829},{"word":"فَإِنَّمَا","ref":"24:52:8","start":1892.829,"end":1894.818},{"word":"عَلَيْهِ","ref":"24:52:9","start":1894.818,"end":1896.409},{"word":"مَا","ref":"24:52:10","start":1896.409,"end":1897.205},{"word":"حُمِّلَ","ref":"24:52:11","start":1897.205,"end":1898.398},{"word":"وَعَلَيْكُم","ref":"24:52:12","start":1898.398,"end":1900.785},{"word":"مَّا","ref":"24:52:13","start":1900.785,"end":1901.581},{"word":"حُمِّلْتُمْۖ","ref":"24:52:14","start":1901.581,"end":1903.57},{"word":"وَإِن","ref":"24:52:15","start":1904.974,"end":1906.287},{"word":"تُطِيعُوهُ","ref":"24:52:16","start":1906.287,"end":1908.914},{"word":"تَهْتَدُواْۖ","ref":"24:52:17","start":1911.196,"end":1912.65},{"word":"وَمَا","ref":"24:52:18","start":1912.65,"end":1913.376},{"word":"عَلَى","ref":"24:52:19","start":1913.376,"end":1913.861},{"word":"اَ۬لرَّسُولِ","ref":"24:52:20","start":1913.861,"end":1915.314},{"word":"إِلَّا","ref":"24:52:21","start":1915.314,"end":1916.041},{"word":"اَ۬لْبَلَٰغُ","ref":"24:52:22","start":1916.041,"end":1917.252},{"word":"اُ۬لْمُبِينُۖ","ref":"24:52:23","start":1917.252,"end":1918.706}]},{"ayah":53,"words":[{"word":"وَعَدَ","ref":"24:53:1","start":1921.326,"end":1922.266},{"word":"اَ۬للَّهُ","ref":"24:53:2","start":1922.266,"end":1923.519},{"word":"اُ۬لذِينَ","ref":"24:53:3","start":1923.519,"end":1925.086},{"word":"ءَامَنُواْ","ref":"24:53:4","start":1925.086,"end":1926.965},{"word":"مِنكُمْ","ref":"24:53:5","start":1926.965,"end":1928.219},{"word":"وَعَمِلُواْ","ref":"24:53:6","start":1928.219,"end":1930.098},{"word":"اُ۬لصَّٰلِحَٰتِ","ref":"24:53:7","start":1930.098,"end":1931.978},{"word":"لَيَسْتَخْلِفَنَّهُمْ","ref":"24:53:8","start":1931.978,"end":1935.111},{"word":"فِے","ref":"24:53:9","start":1935.111,"end":1935.424},{"word":"اِ۬لْأَرْضِ","ref":"24:53:10","start":1935.424,"end":1936.991},{"word":"كَمَا","ref":"24:53:11","start":1936.991,"end":1937.931},{"word":"اَ۪سْتَخْلَفَ","ref":"24:53:12","start":1937.931,"end":1939.81},{"word":"اَ۬لذِينَ","ref":"24:53:13","start":1939.81,"end":1941.377},{"word":"مِن","ref":"24:53:14","start":1941.377,"end":1942.004},{"word":"قَبْلِهِمْ","ref":"24:53:15","start":1942.004,"end":1943.57},{"word":"كَمَا","ref":"24:53:11","start":1946.35,"end":1947.17},{"word":"اَ۪سْتَخْلَفَ","ref":"24:53:12","start":1947.17,"end":1948.81},{"word":"اَ۬لذِينَ","ref":"24:53:13","start":1948.81,"end":1950.176},{"word":"مِن","ref":"24:53:14","start":1950.176,"end":1950.723},{"word":"قَبْلِهِمْ","ref":"24:53:15","start":1950.723,"end":1952.089},{"word":"وَلَيُمَكِّنَنَّ","ref":"24:53:16","start":1952.089,"end":1954.002},{"word":"وَلَيُمَكِّنَنَّ","ref":"24:53:16","start":1954.172,"end":1956.509},{"word":"لَهُمْ","ref":"24:53:17","start":1956.509,"end":1957.51},{"word":"دِينَهُمُ","ref":"24:53:18","start":1957.51,"end":1959.179},{"word":"اُ۬لذِے","ref":"24:53:19","start":1959.179,"end":1960.181},{"word":"اِ۪رْتَضَىٰ","ref":"24:53:20","start":1960.181,"end":1961.516},{"word":"لَهُمْ","ref":"24:53:21","start":1961.516,"end":1962.518},{"word":"وَلَيُبَدِّلَنَّهُم","ref":"24:53:22","start":1962.518,"end":1965.522},{"word":"وَلَيُبَدِّلَنَّهُم","ref":"24:53:22","start":1968.156,"end":1971.996},{"word":"مِّنۢ","ref":"24:53:23","start":1971.996,"end":1972.85},{"word":"بَعْدِ","ref":"24:53:24","start":1972.85,"end":1974.13},{"word":"خَوْفِهِمْ","ref":"24:53:25","start":1974.13,"end":1976.263},{"word":"أَمْناٗۖ","ref":"24:53:26","start":1976.263,"end":1977.97},{"word":"يَعْبُدُونَنِے","ref":"24:53:27","start":1979.708,"end":1982.337},{"word":"لَا","ref":"24:53:28","start":1982.337,"end":1983.088},{"word":"يُشْرِكُونَ","ref":"24:53:29","start":1983.088,"end":1985.341},{"word":"بِے","ref":"24:53:30","start":1985.341,"end":1985.716},{"word":"شَئْاٗۖ","ref":"24:53:31","start":1985.716,"end":1987.218},{"word":"وَمَن","ref":"24:53:32","start":1989.038,"end":1990.262},{"word":"كَفَرَ","ref":"24:53:33","start":1990.262,"end":1991.485},{"word":"بَعْدَ","ref":"24:53:34","start":1991.485,"end":1992.709},{"word":"ذَٰلِكَ","ref":"24:53:35","start":1992.709,"end":1993.932},{"word":"فَأُوْلَٰٓئِكَ","ref":"24:53:36","start":1993.932,"end":1996.379},{"word":"هُمُ","ref":"24:53:37","start":1996.379,"end":1997.195},{"word":"اُ۬لْفَٰسِقُونَۖ","ref":"24:53:38","start":1997.195,"end":2000.05}]},{"ayah":54,"words":[{"word":"وَأَقِيمُواْ","ref":"24:54:1","start":2002.524,"end":2004.493},{"word":"اُ۬لصَّلَوٰةَ","ref":"24:54:2","start":2004.493,"end":2006.18},{"word":"وَءَاتُواْ","ref":"24:54:3","start":2006.18,"end":2007.868},{"word":"اُ۬لزَّكَوٰةَۖ","ref":"24:54:4","start":2007.868,"end":2009.556},{"word":"وَأَطِيعُواْ","ref":"24:54:5","start":2009.556,"end":2011.524},{"word":"اُ۬لرَّسُولَ","ref":"24:54:6","start":2011.524,"end":2013.212},{"word":"لَعَلَّكُمْ","ref":"24:54:7","start":2013.212,"end":2014.618},{"word":"تُرْحَمُونَۖ","ref":"24:54:8","start":2014.618,"end":2016.306}]},{"ayah":55,"words":[{"word":"لَا","ref":"24:55:1","start":2018.446,"end":2019.102},{"word":"تَحْسِبَنَّ","ref":"24:55:2","start":2019.102,"end":2020.741},{"word":"اَ۬لذِينَ","ref":"24:55:3","start":2020.741,"end":2022.38},{"word":"كَفَرُواْ","ref":"24:55:4","start":2022.38,"end":2024.02},{"word":"مُعْجِزِينَ","ref":"24:55:5","start":2024.02,"end":2025.987},{"word":"فِے","ref":"24:55:6","start":2025.987,"end":2026.315},{"word":"اِ۬لْأَرْضِۖ","ref":"24:55:7","start":2026.315,"end":2027.954},{"word":"وَمَأْوَيٰهُمُ","ref":"24:55:8","start":2030.108,"end":2032.547},{"word":"اُ۬لنَّارُۖ","ref":"24:55:9","start":2032.547,"end":2034.29},{"word":"وَلَبِئْسَ","ref":"24:55:10","start":2035.612,"end":2037.447},{"word":"اَ۬لْمَصِيرُۖ","ref":"24:55:11","start":2037.447,"end":2039.282}]},{"ayah":56,"words":[{"word":"يَٰأَيُّهَا","ref":"24:56:1","start":2041.98,"end":2043.541},{"word":"اَ۬لذِينَ","ref":"24:56:2","start":2043.541,"end":2045.102},{"word":"ءَامَنُواْ","ref":"24:56:3","start":2045.102,"end":2046.975},{"word":"لِيَسْتَٰٔذِنكُمُ","ref":"24:56:4","start":2046.975,"end":2049.784},{"word":"اُ۬لذِينَ","ref":"24:56:5","start":2049.784,"end":2051.345},{"word":"مَلَكَتْ","ref":"24:56:6","start":2051.345,"end":2052.594},{"word":"أَيْمَٰنُكُمْ","ref":"24:56:7","start":2052.764,"end":2054.869},{"word":"وَالذِينَ","ref":"24:56:8","start":2054.869,"end":2056.974},{"word":"لَمْ","ref":"24:56:9","start":2056.974,"end":2057.675},{"word":"يَبْلُغُواْ","ref":"24:56:10","start":2057.675,"end":2059.78},{"word":"اُ۬لْحُلُمَ","ref":"24:56:11","start":2059.78,"end":2061.534},{"word":"مِنكُمْ","ref":"24:56:12","start":2061.534,"end":2062.937},{"word":"ثَلَٰثَ","ref":"24:56:13","start":2062.937,"end":2063.99},{"word":"مَرَّٰتٖ","ref":"24:56:14","start":2063.99,"end":2065.042},{"word":"مِّن","ref":"24:56:15","start":2067.982,"end":2068.659},{"word":"قَبْلِ","ref":"24:56:16","start":2068.659,"end":2069.675},{"word":"صَلَوٰةِ","ref":"24:56:17","start":2069.675,"end":2071.03},{"word":"اِ۬لْفَجْرِ","ref":"24:56:18","start":2071.03,"end":2072.724},{"word":"وَحِينَ","ref":"24:56:19","start":2072.724,"end":2074.078},{"word":"تَضَعُونَ","ref":"24:56:20","start":2074.078,"end":2075.772},{"word":"ثِيَابَكُم","ref":"24:56:21","start":2075.772,"end":2077.804},{"word":"مِّنَ","ref":"24:56:22","start":2077.804,"end":2078.481},{"word":"اَ۬لظَّهِيرَةِ","ref":"24:56:23","start":2078.481,"end":2080.852},{"word":"وَمِنۢ","ref":"24:56:24","start":2080.852,"end":2081.868},{"word":"بَعْدِ","ref":"24:56:25","start":2081.868,"end":2082.884},{"word":"صَلَوٰةِ","ref":"24:56:26","start":2082.884,"end":2084.239},{"word":"اِ۬لْعِشَآءِۖ","ref":"24:56:27","start":2084.239,"end":2086.61},{"word":"ثَلَٰثُ","ref":"24:56:28","start":2095.854,"end":2096.688},{"word":"عَوْرَٰتٖ","ref":"24:56:29","start":2096.688,"end":2097.8},{"word":"لَّكُمْۖ","ref":"24:56:30","start":2097.8,"end":2098.635},{"word":"لَيْسَ","ref":"24:56:31","start":2098.635,"end":2099.469},{"word":"عَلَيْكُمْ","ref":"24:56:32","start":2099.469,"end":2100.859},{"word":"وَلَا","ref":"24:56:33","start":2100.859,"end":2101.693},{"word":"عَلَيْهِمْ","ref":"24:56:34","start":2101.693,"end":2103.083},{"word":"جُنَاحُۢ","ref":"24:56:35","start":2103.083,"end":2104.196},{"word":"بَعْدَهُنَّۖ","ref":"24:56:36","start":2104.196,"end":2105.586},{"word":"بَعْدَهُنَّۖ","ref":"24:56:36","start":2107.516,"end":2109.146},{"word":"طَوَّٰفُونَ","ref":"24:56:37","start":2109.146,"end":2110.776},{"word":"عَلَيْكُمۖ","ref":"24:56:38","start":2110.776,"end":2112.406},{"word":"بَعْضُكُمْ","ref":"24:56:39","start":2112.406,"end":2114.036},{"word":"عَلَىٰ","ref":"24:56:40","start":2114.036,"end":2114.688},{"word":"بَعْضٖۖ","ref":"24:56:41","start":2114.688,"end":2115.666},{"word":"كَذَٰلِكَ","ref":"24:56:42","start":2118.406,"end":2119.883},{"word":"يُبَيِّنُ","ref":"24:56:43","start":2119.883,"end":2121.361},{"word":"اُ۬للَّهُ","ref":"24:56:44","start":2121.361,"end":2122.838},{"word":"لَكُمُ","ref":"24:56:45","start":2122.838,"end":2123.946},{"word":"اُ۬لْأٓيَٰتِۖ","ref":"24:56:46","start":2123.946,"end":2126.162},{"word":"وَاللَّهُ","ref":"24:56:47","start":2127.676,"end":2129.617},{"word":"عَلِيمٌ","ref":"24:56:48","start":2129.617,"end":2131.169},{"word":"حَكِيمٞۖ","ref":"24:56:49","start":2131.169,"end":2132.722},{"word":"وَاللَّهُ","ref":"24:56:47","start":2164.028,"end":2165.981},{"word":"عَلِيمٌ","ref":"24:56:48","start":2165.981,"end":2167.544},{"word":"حَكِيمٞۖ","ref":"24:56:49","start":2167.544,"end":2169.106}]},{"ayah":57,"words":[{"word":"وَإِذَا","ref":"24:57:1","start":2135.526,"end":2136.795},{"word":"بَلَغَ","ref":"24:57:2","start":2136.795,"end":2137.746},{"word":"اَ۬لْأَطْفَٰلُ","ref":"24:57:3","start":2137.746,"end":2139.65},{"word":"مِنكُمُ","ref":"24:57:4","start":2139.65,"end":2140.919},{"word":"اُ۬لْحُلُمَ","ref":"24:57:5","start":2140.919,"end":2142.505},{"word":"فَلْيَسْتَٰٔذِنُواْ","ref":"24:57:6","start":2142.505,"end":2145.677},{"word":"كَمَا","ref":"24:57:7","start":2145.677,"end":2146.628},{"word":"اَ۪سْتَٰٔذَنَ","ref":"24:57:8","start":2146.628,"end":2148.532},{"word":"اَ۬لذِينَ","ref":"24:57:9","start":2148.532,"end":2150.118},{"word":"مِن","ref":"24:57:10","start":2150.118,"end":2150.752},{"word":"قَبْلِهِمْۖ","ref":"24:57:11","start":2150.752,"end":2152.338},{"word":"كَذَٰلِكَ","ref":"24:57:12","start":2154.726,"end":2156.203},{"word":"يُبَيِّنُ","ref":"24:57:13","start":2156.203,"end":2157.681},{"word":"اُ۬للَّهُ","ref":"24:57:14","start":2157.681,"end":2159.158},{"word":"لَكُمْ","ref":"24:57:15","start":2159.158,"end":2160.266},{"word":"ءَايَٰتِهِۦۖ","ref":"24:57:16","start":2160.266,"end":2162.482},{"word":"وَإِذَا","ref":"24:57:1","start":2171.974,"end":2172.509},{"word":"بَلَغَ","ref":"24:57:2","start":2172.509,"end":2172.91},{"word":"اَ۬لْأَطْفَٰلُ","ref":"24:57:3","start":2172.91,"end":2173.712},{"word":"مِنكُمُ","ref":"24:57:4","start":2173.712,"end":2174.247},{"word":"اُ۬لْحُلُمَ","ref":"24:57:5","start":2174.247,"end":2174.916},{"word":"فَلْيَسْتَٰٔذِنُواْ","ref":"24:57:6","start":2174.916,"end":2176.253},{"word":"كَمَا","ref":"24:57:7","start":2176.253,"end":2176.654},{"word":"اَ۪سْتَٰٔذَنَ","ref":"24:57:8","start":2176.654,"end":2177.456},{"word":"اَ۬لذِينَ","ref":"24:57:9","start":2177.456,"end":2178.125},{"word":"مِن","ref":"24:57:10","start":2178.125,"end":2178.392},{"word":"قَبْلِهِمْۖ","ref":"24:57:11","start":2178.392,"end":2179.061},{"word":"كَذَٰلِكَ","ref":"24:57:12","start":2179.061,"end":2179.595},{"word":"يُبَيِّنُ","ref":"24:57:13","start":2179.595,"end":2180.13},{"word":"اُ۬للَّهُ","ref":"24:57:14","start":2180.13,"end":2180.665},{"word":"لَكُمْ","ref":"24:57:15","start":2180.665,"end":2181.066},{"word":"ءَايَٰتِهِۦۖ","ref":"24:57:16","start":2181.066,"end":2181.869},{"word":"وَاللَّهُ","ref":"24:57:17","start":2181.869,"end":2182.537},{"word":"عَلِيمٌ","ref":"24:57:18","start":2182.537,"end":2183.072},{"word":"حَكِيمٞۖ","ref":"24:57:19","start":2183.072,"end":2183.607}]},{"ayah":58,"words":[{"word":"۞","ref":"24:58:1","start":2183.607,"end":2183.607},{"word":"وَالْقَوَٰعِدُ","ref":"24:58:2","start":2183.607,"end":2184.543},{"word":"مِنَ","ref":"24:58:3","start":2184.543,"end":2184.81},{"word":"اَ۬لنِّسَآءِ","ref":"24:58:4","start":2184.81,"end":2185.746},{"word":"اِ۬لَّٰتِے","ref":"24:58:5","start":2185.746,"end":2186.147},{"word":"لَا","ref":"24:58:6","start":2186.147,"end":2186.415},{"word":"يَرْجُونَ","ref":"24:58:7","start":2186.415,"end":2187.083},{"word":"نِكَاحاٗ","ref":"24:58:8","start":2187.083,"end":2187.752},{"word":"فَلَيْسَ","ref":"24:58:9","start":2187.752,"end":2188.287},{"word":"عَلَيْهِنَّ","ref":"24:58:10","start":2188.287,"end":2188.955},{"word":"جُنَاحٌ","ref":"24:58:11","start":2188.955,"end":2189.49},{"word":"نِكَاحاٗ","ref":"24:58:8","start":2192.22,"end":2194.07},{"word":"فَلَيْسَ","ref":"24:58:9","start":2194.07,"end":2195.55},{"word":"عَلَيْهِنَّ","ref":"24:58:10","start":2195.55,"end":2197.399},{"word":"جُنَاحٌ","ref":"24:58:11","start":2197.399,"end":2198.879},{"word":"أَنْ","ref":"24:58:12","start":2198.879,"end":2199.619},{"word":"يَّضَعْنَ","ref":"24:58:13","start":2199.619,"end":2201.099},{"word":"ثِيَابَهُنَّ","ref":"24:58:14","start":2201.099,"end":2203.319},{"word":"غَيْرَ","ref":"24:58:15","start":2203.319,"end":2204.428},{"word":"مُتَبَرِّجَٰتِۢ","ref":"24:58:16","start":2204.428,"end":2206.648},{"word":"بِزِينَةٖۖ","ref":"24:58:17","start":2206.648,"end":2208.498},{"word":"وَأَنْ","ref":"24:58:18","start":2210.734,"end":2211.971},{"word":"يَّسْتَعْفِفْنَ","ref":"24:58:19","start":2211.971,"end":2214.856},{"word":"خَيْرٞ","ref":"24:58:20","start":2214.856,"end":2216.093},{"word":"لَّهُنَّۖ","ref":"24:58:21","start":2216.093,"end":2217.33},{"word":"وَاللَّهُ","ref":"24:58:22","start":2219.036,"end":2220.989},{"word":"سَمِيعٌ","ref":"24:58:23","start":2220.989,"end":2222.552},{"word":"عَلِيمٞۖ","ref":"24:58:24","start":2222.552,"end":2224.114}]},{"ayah":59,"words":[{"word":"لَّيْسَ","ref":"24:59:1","start":2227.118,"end":2228.662},{"word":"عَلَى","ref":"24:59:2","start":2228.662,"end":2229.691},{"word":"اَ۬لْأَعْمَىٰ","ref":"24:59:3","start":2229.691,"end":2232.263},{"word":"حَرَجٞ","ref":"24:59:4","start":2232.263,"end":2233.807},{"word":"وَلَا","ref":"24:59:5","start":2233.807,"end":2235.35},{"word":"عَلَى","ref":"24:59:6","start":2235.35,"end":2236.379},{"word":"اَ۬لْأَعْرَجِ","ref":"24:59:7","start":2236.379,"end":2239.466},{"word":"حَرَجٞ","ref":"24:59:8","start":2239.466,"end":2241.01},{"word":"وَلَا","ref":"24:59:9","start":2243.886,"end":2245.078},{"word":"عَلَى","ref":"24:59:10","start":2245.078,"end":2245.872},{"word":"اَ۬لْمَرِيضِ","ref":"24:59:11","start":2245.872,"end":2248.255},{"word":"حَرَجٞ","ref":"24:59:12","start":2248.255,"end":2249.447},{"word":"وَلَا","ref":"24:59:13","start":2249.447,"end":2250.638},{"word":"عَلَىٰ","ref":"24:59:14","start":2250.638,"end":2251.433},{"word":"أَنفُسِكُمْ","ref":"24:59:15","start":2251.433,"end":2253.816},{"word":"أَن","ref":"24:59:16","start":2253.816,"end":2254.61},{"word":"تَأْكُلُواْ","ref":"24:59:17","start":2254.876,"end":2256.979},{"word":"مِنۢ","ref":"24:59:18","start":2256.979,"end":2257.68},{"word":"بِيُوتِكُمْ","ref":"24:59:19","start":2257.68,"end":2259.782},{"word":"أَوْ","ref":"24:59:20","start":2259.782,"end":2260.483},{"word":"بِيُوتِ","ref":"24:59:21","start":2260.483,"end":2261.885},{"word":"ءَابَآئِكُمْ","ref":"24:59:22","start":2261.885,"end":2264.338},{"word":"أَوْ","ref":"24:59:20","start":2267.214,"end":2267.985},{"word":"بِيُوتِ","ref":"24:59:21","start":2267.985,"end":2269.526},{"word":"ءَابَآئِكُمْ","ref":"24:59:22","start":2269.526,"end":2272.224},{"word":"أَوْ","ref":"24:59:23","start":2272.224,"end":2272.995},{"word":"بِيُوتِ","ref":"24:59:24","start":2272.995,"end":2274.536},{"word":"أُمَّهَٰتِكُمْ","ref":"24:59:25","start":2274.536,"end":2276.849},{"word":"أَوْ","ref":"24:59:26","start":2276.849,"end":2277.619},{"word":"بِيُوتِ","ref":"24:59:27","start":2277.619,"end":2279.161},{"word":"إِخْوَٰنِكُمْ","ref":"24:59:28","start":2279.161,"end":2281.473},{"word":"أَوْ","ref":"24:59:29","start":2281.473,"end":2282.244},{"word":"بِيُوتِ","ref":"24:59:30","start":2282.244,"end":2283.786},{"word":"أَخَوَٰتِكُمْ","ref":"24:59:31","start":2283.786,"end":2286.098},{"word":"أَوْ","ref":"24:59:29","start":2289.55,"end":2290.552},{"word":"بِيُوتِ","ref":"24:59:30","start":2290.552,"end":2292.557},{"word":"أَخَوَٰتِكُمْ","ref":"24:59:31","start":2292.557,"end":2295.564},{"word":"أَوْ","ref":"24:59:32","start":2295.564,"end":2296.566},{"word":"بِيُوتِ","ref":"24:59:33","start":2296.566,"end":2298.571},{"word":"أَعْمَٰمِكُمْ","ref":"24:59:34","start":2298.571,"end":2301.577},{"word":"أَوْ","ref":"24:59:35","start":2301.577,"end":2302.58},{"word":"بِيُوتِ","ref":"24:59:36","start":2302.58,"end":2304.584},{"word":"عَمَّٰتِكُمْ","ref":"24:59:37","start":2304.584,"end":2307.09},{"word":"أَوْ","ref":"24:59:38","start":2310.254,"end":2310.914},{"word":"بِيُوتِ","ref":"24:59:39","start":2310.914,"end":2312.235},{"word":"أَخْوَٰلِكُمْ","ref":"24:59:40","start":2312.235,"end":2314.215},{"word":"أَوْ","ref":"24:59:41","start":2314.215,"end":2314.876},{"word":"بِيُوتِ","ref":"24:59:42","start":2314.876,"end":2316.196},{"word":"خَٰلَٰتِكُمْ","ref":"24:59:43","start":2316.196,"end":2317.847},{"word":"أَوْ","ref":"24:59:44","start":2317.847,"end":2318.507},{"word":"مَا","ref":"24:59:45","start":2318.507,"end":2319.167},{"word":"مَلَكْتُم","ref":"24:59:46","start":2319.167,"end":2320.818},{"word":"مَلَكْتُم","ref":"24:59:46","start":2321.02,"end":2322.57},{"word":"مَّفَاتِحَهُۥ","ref":"24:59:47","start":2322.57,"end":2324.739},{"word":"أَوْ","ref":"24:59:48","start":2324.739,"end":2325.359},{"word":"صَدِيقِكُمْۖ","ref":"24:59:49","start":2325.359,"end":2327.218},{"word":"لَيْسَ","ref":"24:59:50","start":2329.838,"end":2331.094},{"word":"عَلَيْكُمْ","ref":"24:59:51","start":2331.094,"end":2333.187},{"word":"جُنَاحٌ","ref":"24:59:52","start":2333.187,"end":2334.861},{"word":"أَن","ref":"24:59:53","start":2334.861,"end":2335.698},{"word":"تَأْكُلُواْ","ref":"24:59:54","start":2335.932,"end":2337.748},{"word":"جَمِيعاً","ref":"24:59:55","start":2337.748,"end":2339.261},{"word":"أَوْ","ref":"24:59:56","start":2339.261,"end":2339.866},{"word":"أَشْتَاتاٗۖ","ref":"24:59:57","start":2339.866,"end":2341.682},{"word":"فَإِذَا","ref":"24:59:58","start":2344.71,"end":2346.447},{"word":"دَخَلْتُم","ref":"24:59:59","start":2346.447,"end":2348.617},{"word":"بِيُوتاٗ","ref":"24:59:60","start":2348.617,"end":2350.788},{"word":"فَسَلِّمُواْ","ref":"24:59:61","start":2350.788,"end":2353.393},{"word":"عَلَىٰ","ref":"24:59:62","start":2353.393,"end":2354.262},{"word":"أَنفُسِكُمْ","ref":"24:59:63","start":2354.262,"end":2356.866},{"word":"تَحِيَّةٗ","ref":"24:59:64","start":2356.866,"end":2358.603},{"word":"مِّنْ","ref":"24:59:65","start":2358.603,"end":2359.471},{"word":"عِندِ","ref":"24:59:66","start":2359.471,"end":2360.774},{"word":"اِ۬للَّهِ","ref":"24:59:67","start":2360.774,"end":2362.511},{"word":"مُبَٰرَكَةٗ","ref":"24:59:68","start":2362.511,"end":2364.681},{"word":"طَيِّبَةٗۖ","ref":"24:59:69","start":2364.681,"end":2366.418},{"word":"كَذَٰلِكَ","ref":"24:59:70","start":2369.222,"end":2370.732},{"word":"يُبَيِّنُ","ref":"24:59:71","start":2370.732,"end":2372.241},{"word":"اُ۬للَّهُ","ref":"24:59:72","start":2372.241,"end":2373.751},{"word":"لَكُمُ","ref":"24:59:73","start":2373.751,"end":2374.883},{"word":"اُ۬لْأٓيَٰتِ","ref":"24:59:74","start":2374.883,"end":2377.147},{"word":"لَعَلَّكُمْ","ref":"24:59:75","start":2377.147,"end":2379.034},{"word":"تَعْقِلُونَۖ","ref":"24:59:76","start":2379.034,"end":2381.298}]},{"ayah":60,"words":[{"word":"إِنَّمَا","ref":"24:60:1","start":2383.206,"end":2384.463},{"word":"اَ۬لْمُؤْمِنُونَ","ref":"24:60:2","start":2384.463,"end":2386.661},{"word":"اَ۬لذِينَ","ref":"24:60:3","start":2386.661,"end":2388.232},{"word":"ءَامَنُواْ","ref":"24:60:4","start":2388.232,"end":2390.117},{"word":"بِاللَّهِ","ref":"24:60:5","start":2390.117,"end":2391.687},{"word":"وَرَسُولِهِۦ","ref":"24:60:6","start":2391.687,"end":2393.886},{"word":"وَإِذَا","ref":"24:60:7","start":2393.886,"end":2395.143},{"word":"كَانُواْ","ref":"24:60:8","start":2395.143,"end":2396.713},{"word":"مَعَهُۥ","ref":"24:60:9","start":2396.713,"end":2397.97},{"word":"وَإِذَا","ref":"24:60:7","start":2400.582,"end":2402.023},{"word":"كَانُواْ","ref":"24:60:8","start":2402.023,"end":2403.825},{"word":"مَعَهُۥ","ref":"24:60:9","start":2403.825,"end":2405.267},{"word":"عَلَىٰ","ref":"24:60:10","start":2405.267,"end":2405.988},{"word":"أَمْرٖ","ref":"24:60:11","start":2405.988,"end":2407.069},{"word":"جَامِعٖ","ref":"24:60:12","start":2407.069,"end":2408.51},{"word":"لَّمْ","ref":"24:60:13","start":2408.51,"end":2409.231},{"word":"يَذْهَبُواْ","ref":"24:60:14","start":2409.231,"end":2411.393},{"word":"حَتَّىٰ","ref":"24:60:15","start":2411.393,"end":2412.114},{"word":"يَسْتَٰٔذِنُوهُۖ","ref":"24:60:16","start":2418.46,"end":2421.023},{"word":"إِنَّ","ref":"24:60:17","start":2421.023,"end":2421.664},{"word":"اَ۬لذِينَ","ref":"24:60:18","start":2421.664,"end":2423.266},{"word":"يَسْتَٰٔذِنُونَكَ","ref":"24:60:19","start":2423.266,"end":2426.15},{"word":"أُوْلَٰٓئِكَ","ref":"24:60:20","start":2426.15,"end":2427.753},{"word":"اَ۬لذِينَ","ref":"24:60:21","start":2427.753,"end":2429.355},{"word":"يُؤْمِنُونَ","ref":"24:60:22","start":2429.355,"end":2430.957},{"word":"بِاللَّهِ","ref":"24:60:23","start":2430.957,"end":2432.559},{"word":"وَرَسُولِهِۦۖ","ref":"24:60:24","start":2432.559,"end":2434.802},{"word":"فَإِذَا","ref":"24:60:25","start":2438.118,"end":2439.093},{"word":"اَ۪سْتَٰٔذَنُوكَ","ref":"24:60:26","start":2439.093,"end":2441.044},{"word":"لِبَعْضِ","ref":"24:60:27","start":2441.044,"end":2442.02},{"word":"شَأْنِهِمْ","ref":"24:60:28","start":2442.02,"end":2443.239},{"word":"فَأْذَن","ref":"24:60:29","start":2443.239,"end":2444.214},{"word":"لِّمَن","ref":"24:60:30","start":2444.214,"end":2444.946},{"word":"شِئْتَ","ref":"24:60:31","start":2447.942,"end":2449.102},{"word":"مِنْهُمْ","ref":"24:60:32","start":2449.102,"end":2450.262},{"word":"وَاسْتَغْفِرْ","ref":"24:60:33","start":2450.262,"end":2452.292},{"word":"لَهُمُ","ref":"24:60:34","start":2452.292,"end":2453.162},{"word":"اُ۬للَّهَۖ","ref":"24:60:35","start":2453.162,"end":2454.322},{"word":"إِنَّ","ref":"24:60:36","start":2457.006,"end":2457.903},{"word":"اَ۬للَّهَ","ref":"24:60:37","start":2457.903,"end":2459.696},{"word":"غَفُورٞ","ref":"24:60:38","start":2459.696,"end":2461.489},{"word":"رَّحِيمٞۖ","ref":"24:60:39","start":2461.489,"end":2463.282}]},{"ayah":61,"words":[{"word":"۞","ref":"24:61:1","start":2465.774,"end":2465.774},{"word":"لَّا","ref":"24:61:2","start":2465.774,"end":2466.498},{"word":"تَجْعَلُواْ","ref":"24:61:3","start":2466.498,"end":2468.67},{"word":"دُعَآءَ","ref":"24:61:4","start":2468.67,"end":2470.479},{"word":"اَ۬لرَّسُولِ","ref":"24:61:5","start":2470.479,"end":2472.651},{"word":"بَيْنَكُمْ","ref":"24:61:6","start":2472.651,"end":2474.461},{"word":"كَدُعَآءِ","ref":"24:61:7","start":2474.461,"end":2476.632},{"word":"بَعْضِكُم","ref":"24:61:8","start":2476.632,"end":2478.442},{"word":"بَعْضاٗۖ","ref":"24:61:9","start":2478.442,"end":2479.89},{"word":"قَدْ","ref":"24:61:10","start":2483.278,"end":2483.98},{"word":"يَعْلَمُ","ref":"24:61:11","start":2483.98,"end":2485.385},{"word":"اُ۬للَّهُ","ref":"24:61:12","start":2485.385,"end":2486.789},{"word":"اُ۬لذِينَ","ref":"24:61:13","start":2486.789,"end":2488.544},{"word":"يَتَسَلَّلُونَ","ref":"24:61:14","start":2488.544,"end":2491.002},{"word":"مِنكُمْ","ref":"24:61:15","start":2491.002,"end":2492.407},{"word":"لِوَاذاٗۖ","ref":"24:61:16","start":2492.407,"end":2494.162},{"word":"فَلْيَحْذَرِ","ref":"24:61:17","start":2498.684,"end":2500.654},{"word":"اِ۬لذِينَ","ref":"24:61:18","start":2500.654,"end":2502.295},{"word":"يُخَالِفُونَ","ref":"24:61:19","start":2502.295,"end":2504.593},{"word":"عَنْ","ref":"24:61:20","start":2504.593,"end":2505.249},{"word":"أَمْرِهِۦ","ref":"24:61:21","start":2505.249,"end":2506.891},{"word":"أَن","ref":"24:61:22","start":2506.891,"end":2507.547},{"word":"تُصِيبَهُمْ","ref":"24:61:23","start":2507.547,"end":2509.517},{"word":"فِتْنَةٌ","ref":"24:61:24","start":2509.517,"end":2510.83},{"word":"أَوْ","ref":"24:61:25","start":2510.83,"end":2511.486},{"word":"يُصِيبَهُمْ","ref":"24:61:26","start":2511.486,"end":2513.456},{"word":"عَذَابٌ","ref":"24:61:27","start":2513.456,"end":2514.769},{"word":"أَلِيمٌۖ","ref":"24:61:28","start":2514.769,"end":2516.082}]},{"ayah":62,"words":[{"word":"أَلَا","ref":"24:62:1","start":2518.382,"end":2519.823},{"word":"إِنَّ","ref":"24:62:2","start":2519.823,"end":2520.784},{"word":"لِلهِ","ref":"24:62:3","start":2520.784,"end":2522.225},{"word":"مَا","ref":"24:62:4","start":2522.225,"end":2523.186},{"word":"فِے","ref":"24:62:5","start":2523.186,"end":2523.666},{"word":"اِ۬لسَّمَٰوَٰتِ","ref":"24:62:6","start":2523.772,"end":2525.479},{"word":"وَالْأَرْضِۖ","ref":"24:62:7","start":2525.479,"end":2527.186},{"word":"قَدْ","ref":"24:62:8","start":2529.774,"end":2530.557},{"word":"يَعْلَمُ","ref":"24:62:9","start":2530.557,"end":2532.124},{"word":"مَا","ref":"24:62:10","start":2532.124,"end":2532.907},{"word":"أَنتُمْ","ref":"24:62:11","start":2532.907,"end":2534.473},{"word":"عَلَيْهِۖ","ref":"24:62:12","start":2534.473,"end":2536.04},{"word":"وَيَوْمَ","ref":"24:62:13","start":2536.04,"end":2537.606},{"word":"يُرْجَعُونَ","ref":"24:62:14","start":2537.606,"end":2539.956},{"word":"إِلَيْهِ","ref":"24:62:15","start":2539.956,"end":2541.522},{"word":"فَيُنَبِّئُهُم","ref":"24:62:16","start":2541.788,"end":2543.879},{"word":"بِمَا","ref":"24:62:17","start":2543.879,"end":2544.663},{"word":"عَمِلُواْۖ","ref":"24:62:18","start":2544.663,"end":2545.97},{"word":"وَاللَّهُ","ref":"24:62:19","start":2548.028,"end":2550.333},{"word":"بِكُلِّ","ref":"24:62:20","start":2550.333,"end":2551.716},{"word":"شَےْءٍ","ref":"24:62:21","start":2551.716,"end":2552.638},{"word":"عَلِيمُۢۖ","ref":"24:62:22","start":2552.638,"end":2554.482}]}]}